{"log": {"version": "1.2", "creator": {"name": "BrowserMob Proxy", "version": "2.1.4", "comment": ""}, "pages": [{"id": "Duane Hall", "startedDateTime": "2021-10-17T12:05:42.283-06:00", "title": "Duane Hall", "pageTimings": {"comment": ""}, "comment": ""}], "entries": [{"pageref": "Duane Hall", "startedDateTime": "2021-10-17T12:05:42.283-06:00", "request": {"method": "GET", "url": "http://voteforhallward6.ca/", "httpVersion": "HTTP/1.1", "cookies": [], "headers": [{"name": "Host", "value": "voteforhallward6.ca"}, {"name": "User-Agent", "value": "Mozilla/5.0 (Windows NT 10.0; Win64; x64; rv:93.0) Gecko/20100101 Firefox/93.0"}, {"name": "Accept", "value": "text/html,application/xhtml+xml,application/xml;q=0.9,image/avif,image/webp,*/*;q=0.8"}, {"name": "Accept-Language", "value": "en-US,en;q=0.5"}, {"name": "Accept-Encoding", "value": "gzip, deflate"}, {"name": "Connection", "value": "keep-alive"}, {"name": "Upgrade-Insecure-Requests", "value": "1"}], "queryString": [], "headersSize": 379, "bodySize": 0, "comment": ""}, "response": {"status": 301, "statusText": "Moved Permanently", "httpVersion": "HTTP/1.1", "cookies": [], "headers": [{"name": "Age", "value": "0"}, {"name": "Date", "value": "Sun, 17 Oct 2021 18:05:42 GMT"}, {"name": "Location", "value": "https://www.voteforhallward6.ca/"}, {"name": "Server", "value": "Squarespace"}, {"name": "Set-Cookie", "value": "crumb=BeTQSD3BJx8oZWE3NTJkODEyNWQxOTk0MTc5NTgyYjcyOTg1MjM1;Path=/"}, {"name": "X-Contextid", "value": "gLWDWujI/8snS9Ter"}, {"name": "Content-Length", "value": "0"}], "content": {"size": 0, "mimeType": "", "comment": ""}, "redirectURL": "https://www.voteforhallward6.ca/", "headersSize": 276, "bodySize": 0, "comment": ""}, "cache": {}, "timings": {"comment": "", "wait": 151, "send": 0, "dns": 70, "ssl": -1, "connect": 56, "blocked": 0, "receive": 0}, "serverIPAddress": "198.185.159.145", "comment": "", "time": 278}, {"pageref": "Duane Hall", "startedDateTime": "2021-10-17T12:05:46.801-06:00", "request": {"method": "GET", "url": "https://www.voteforhallward6.ca/", "httpVersion": "HTTP/1.1", "cookies": [], "headers": [{"name": "Host", "value": "www.voteforhallward6.ca"}, {"name": "User-Agent", "value": "Mozilla/5.0 (Windows NT 10.0; Win64; x64; rv:93.0) Gecko/20100101 Firefox/93.0"}, {"name": "Accept", "value": "text/html,application/xhtml+xml,application/xml;q=0.9,image/avif,image/webp,*/*;q=0.8"}, {"name": "Accept-Language", "value": "en-US,en;q=0.5"}, {"name": "Accept-Encoding", "value": "gzip, deflate, br"}, {"name": "Connection", "value": "keep-alive"}, {"name": "Upgrade-Insecure-Requests", "value": "1"}, {"name": "Sec-Fetch-Dest", "value": "document"}, {"name": "Sec-Fetch-Mode", "value": "navigate"}, {"name": "Sec-Fetch-Site", "value": "none"}, {"name": "Sec-Fetch-User", "value": "?1"}], "queryString": [], "headersSize": 455, "bodySize": 0, "comment": ""}, "response": {"status": 200, "statusText": "OK", "httpVersion": "HTTP/1.1", "cookies": [], "headers": [{"name": "Accept-Ranges", "value": "bytes"}, {"name": "Age", "value": "152902"}, {"name": "Content-Encoding", "value": "gzip"}, {"name": "Content-Length", "value": "12050"}, {"name": "Content-Type", "value": "text/html;charset=utf-8"}, {"name": "Date", "value": "Fri, 15 Oct 2021 23:37:24 GMT"}, {"name": "Etag", "value": "W/\"16fec7b12e3b690c8898e18659f0533f\""}, {"name": "Expires", "value": "Thu, 01 Jan 1970 00:00:00 GMT"}, {"name": "Server", "value": "Squarespace"}, {"name": "Set-Cookie", "value": "crumb=BTDwk43FTzXnNzFmM2IzMTg4OTA5NzNkNTQyYjJlYmQzOGM5NmVh;Path=/"}, {"name": "Strict-Transport-Security", "value": "max-age=43200"}, {"name": "Vary", "value": "Accept-Encoding"}, {"name": "X-Content-Type-Options", "value": "nosniff"}, {"name": "X-Contextid", "value": "FQR9dZRM/DlbyqqHD"}], "content": {"size": 0, "mimeType": "text/html;charset=utf-8", "comment": ""}, "redirectURL": "", "headersSize": 493, "bodySize": 12050, "comment": ""}, "cache": {}, "timings": {"comment": "", "wait": 101, "send": 0, "dns": 77, "ssl": 4092, "connect": 4146, "blocked": 0, "receive": 51}, "serverIPAddress": "198.185.159.145", "comment": "", "time": 4377}, {"pageref": "Duane Hall", "startedDateTime": "2021-10-17T12:05:46.932-06:00", "request": {"method": "GET", "url": "https://assets.squarespace.com/@sqs/polyfiller/1.2.2/modern.js", "httpVersion": "HTTP/1.1", "cookies": [], "headers": [{"name": "Host", "value": "assets.squarespace.com"}, {"name": "User-Agent", "value": "Mozilla/5.0 (Windows NT 10.0; Win64; x64; rv:93.0) Gecko/20100101 Firefox/93.0"}, {"name": "Accept", "value": "*/*"}, {"name": "Accept-Language", "value": "en-US,en;q=0.5"}, {"name": "Accept-Encoding", "value": "gzip, deflate, br"}, {"name": "Origin", "value": "https://www.voteforhallward6.ca"}, {"name": "Connection", "value": "keep-alive"}, {"name": "Referer", "value": "https://www.voteforhallward6.ca/"}, {"name": "Sec-Fetch-Dest", "value": "script"}, {"name": "Sec-Fetch-Mode", "value": "cors"}, {"name": "Sec-Fetch-Site", "value": "cross-site"}], "queryString": [], "headersSize": 437, "bodySize": 0, "comment": ""}, "response": {"status": 200, "statusText": "OK", "httpVersion": "HTTP/1.1", "cookies": [], "headers": [{"name": "Connection", "value": "keep-alive"}, {"name": "Content-Length", "value": "29224"}, {"name": "Cache-Control", "value": "public, max-age=31536000"}, {"name": "Expires", "value": "Fri, 09 Sep 2022 19:36:46 GMT"}, {"name": "Last-Modified", "value": "Wed, 08 Sep 2021 20:21:24 GMT"}, {"name": "ETag", "value": "\"03e5ef7c77d113abf6178fce61ec6344\""}, {"name": "Content-Type", "value": "text/javascript"}, {"name": "Content-Encoding", "value": "gzip"}, {"name": "Server", "value": "UploadServer"}, {"name": "Via", "value": "1.1 varnish, 1.1 varnish"}, {"name": "Accept-Ranges", "value": "bytes"}, {"name": "Date", "value": "Sun, 17 Oct 2021 18:05:47 GMT"}, {"name": "Age", "value": "3277740"}, {"name": "X-Served-By", "value": "cache-bwi5128-BWI, cache-sea4434-SEA"}, {"name": "X-Cache", "value": "HIT, HIT"}, {"name": "X-Cache-Hits", "value": "1, 296754"}, {"name": "X-Timer", "value": "S1634493947.227665,VS0,VE0"}, {"name": "Vary", "value": "Accept-Encoding"}, {"name": "Access-Control-Allow-Methods", "value": "GET, OPTIONS"}, {"name": "Access-Control-Allow-Origin", "value": "*"}], "content": {"size": 0, "mimeType": "text/javascript", "comment": ""}, "redirectURL": "", "headersSize": 649, "bodySize": 29224, "comment": ""}, "cache": {}, "timings": {"comment": "", "wait": 23, "send": 0, "dns": -1, "ssl": -1, "connect": -1, "blocked": -1, "receive": 9}, "serverIPAddress": "151.101.52.237", "comment": "", "time": 33}, {"pageref": "Duane Hall", "startedDateTime": "2021-10-17T12:05:46.932-06:00", "request": {"method": "GET", "url": "https://assets.squarespace.com/universal/scripts-compressed/moment-js-vendor-26ddeab7fa5f90b6c8cb3-min.en-US.js", "httpVersion": "HTTP/1.1", "cookies": [], "headers": [{"name": "Host", "value": "assets.squarespace.com"}, {"name": "User-Agent", "value": "Mozilla/5.0 (Windows NT 10.0; Win64; x64; rv:93.0) Gecko/20100101 Firefox/93.0"}, {"name": "Accept", "value": "*/*"}, {"name": "Accept-Language", "value": "en-US,en;q=0.5"}, {"name": "Accept-Encoding", "value": "gzip, deflate, br"}, {"name": "Origin", "value": "https://www.voteforhallward6.ca"}, {"name": "Connection", "value": "keep-alive"}, {"name": "Referer", "value": "https://www.voteforhallward6.ca/"}, {"name": "Sec-Fetch-Dest", "value": "script"}, {"name": "Sec-Fetch-Mode", "value": "cors"}, {"name": "Sec-Fetch-Site", "value": "cross-site"}], "queryString": [], "headersSize": 486, "bodySize": 0, "comment": ""}, "response": {"status": 200, "statusText": "OK", "httpVersion": "HTTP/1.1", "cookies": [], "headers": [{"name": "Connection", "value": "keep-alive"}, {"name": "Content-Length", "value": "39407"}, {"name": "Cache-Control", "value": "public, max-age=31536000"}, {"name": "Expires", "value": "Fri, 05 Aug 2022 07:03:23 GMT"}, {"name": "Last-Modified", "value": "Thu, 18 Mar 2021 14:44:33 GMT"}, {"name": "ETag", "value": "\"a5300ca56968fb06474b320df47af1b8\""}, {"name": "Content-Type", "value": "text/javascript"}, {"name": "Content-Encoding", "value": "br"}, {"name": "Server", "value": "UploadServer"}, {"name": "Via", "value": "1.1 varnish, 1.1 varnish"}, {"name": "Accept-Ranges", "value": "bytes"}, {"name": "Date", "value": "Sun, 17 Oct 2021 18:05:47 GMT"}, {"name": "Age", "value": "6346945"}, {"name": "X-Served-By", "value": "cache-bwi5178-BWI, cache-sea4456-SEA"}, {"name": "X-Cache", "value": "HIT, HIT"}, {"name": "X-Cache-Hits", "value": "1, 174770"}, {"name": "X-Timer", "value": "S1634493947.226493,VS0,VE0"}, {"name": "Vary", "value": "Accept-Encoding"}, {"name": "Access-Control-Allow-Methods", "value": "GET, OPTIONS"}, {"name": "Access-Control-Allow-Origin", "value": "*"}], "content": {"size": 0, "mimeType": "text/javascript", "comment": ""}, "redirectURL": "", "headersSize": 647, "bodySize": 39407, "comment": ""}, "cache": {}, "timings": {"comment": "", "wait": 20, "send": 0, "dns": -1, "ssl": -1, "connect": -1, "blocked": -1, "receive": 25}, "serverIPAddress": "151.101.52.237", "comment": "", "time": 45}, {"pageref": "Duane Hall", "startedDateTime": "2021-10-17T12:05:46.932-06:00", "request": {"method": "GET", "url": "https://assets.squarespace.com/universal/scripts-compressed/cldr-resource-pack-be81d1ce004cbca505842-min.en-US.js", "httpVersion": "HTTP/1.1", "cookies": [], "headers": [{"name": "Host", "value": "assets.squarespace.com"}, {"name": "User-Agent", "value": "Mozilla/5.0 (Windows NT 10.0; Win64; x64; rv:93.0) Gecko/20100101 Firefox/93.0"}, {"name": "Accept", "value": "*/*"}, {"name": "Accept-Language", "value": "en-US,en;q=0.5"}, {"name": "Accept-Encoding", "value": "gzip, deflate, br"}, {"name": "Origin", "value": "https://www.voteforhallward6.ca"}, {"name": "Connection", "value": "keep-alive"}, {"name": "Referer", "value": "https://www.voteforhallward6.ca/"}, {"name": "Sec-Fetch-Dest", "value": "script"}, {"name": "Sec-Fetch-Mode", "value": "cors"}, {"name": "Sec-Fetch-Site", "value": "cross-site"}], "queryString": [], "headersSize": 488, "bodySize": 0, "comment": ""}, "response": {"status": 200, "statusText": "OK", "httpVersion": "HTTP/1.1", "cookies": [], "headers": [{"name": "Connection", "value": "keep-alive"}, {"name": "Content-Length", "value": "18586"}, {"name": "Cache-Control", "value": "public, max-age=31536000"}, {"name": "Expires", "value": "Fri, 16 Sep 2022 08:28:59 GMT"}, {"name": "Last-Modified", "value": "Thu, 12 Aug 2021 19:53:19 GMT"}, {"name": "ETag", "value": "\"a588b99d79f93137324ae7b20205d8c5\""}, {"name": "Content-Type", "value": "text/javascript"}, {"name": "Content-Encoding", "value": "br"}, {"name": "Server", "value": "UploadServer"}, {"name": "Via", "value": "1.1 varnish, 1.1 varnish"}, {"name": "Accept-Ranges", "value": "bytes"}, {"name": "Date", "value": "Sun, 17 Oct 2021 18:05:47 GMT"}, {"name": "Age", "value": "2713007"}, {"name": "X-Served-By", "value": "cache-bwi5169-BWI, cache-sea4453-SEA"}, {"name": "X-Cache", "value": "HIT, HIT"}, {"name": "X-Cache-Hits", "value": "1, 50726"}, {"name": "X-Timer", "value": "S1634493947.226312,VS0,VE0"}, {"name": "Vary", "value": "Accept-Encoding"}, {"name": "Access-Control-Allow-Methods", "value": "GET, OPTIONS"}, {"name": "Access-Control-Allow-Origin", "value": "*"}], "content": {"size": 0, "mimeType": "text/javascript", "comment": ""}, "redirectURL": "", "headersSize": 646, "bodySize": 18586, "comment": ""}, "cache": {}, "timings": {"comment": "", "wait": 19, "send": 0, "dns": -1, "ssl": -1, "connect": -1, "blocked": -1, "receive": 15}, "serverIPAddress": "151.101.52.237", "comment": "", "time": 35}, {"pageref": "Duane Hall", "startedDateTime": "2021-10-17T12:05:46.932-06:00", "request": {"method": "GET", "url": "https://assets.squarespace.com/universal/scripts-compressed/common-vendors-stable-5f58a0e5b599c258afba7-min.en-US.js", "httpVersion": "HTTP/1.1", "cookies": [], "headers": [{"name": "Host", "value": "assets.squarespace.com"}, {"name": "User-Agent", "value": "Mozilla/5.0 (Windows NT 10.0; Win64; x64; rv:93.0) Gecko/20100101 Firefox/93.0"}, {"name": "Accept", "value": "*/*"}, {"name": "Accept-Language", "value": "en-US,en;q=0.5"}, {"name": "Accept-Encoding", "value": "gzip, deflate, br"}, {"name": "Origin", "value": "https://www.voteforhallward6.ca"}, {"name": "Connection", "value": "keep-alive"}, {"name": "Referer", "value": "https://www.voteforhallward6.ca/"}, {"name": "Sec-Fetch-Dest", "value": "script"}, {"name": "Sec-Fetch-Mode", "value": "cors"}, {"name": "Sec-Fetch-Site", "value": "cross-site"}], "queryString": [], "headersSize": 491, "bodySize": 0, "comment": ""}, "response": {"status": 200, "statusText": "OK", "httpVersion": "HTTP/1.1", "cookies": [], "headers": [{"name": "Connection", "value": "keep-alive"}, {"name": "Content-Length", "value": "67156"}, {"name": "Cache-Control", "value": "public, max-age=31536000"}, {"name": "Expires", "value": "Tue, 16 Aug 2022 16:26:54 GMT"}, {"name": "Last-Modified", "value": "Mon, 16 Aug 2021 15:37:49 GMT"}, {"name": "ETag", "value": "\"aea3f37992c4b4d335d95084a7af011c\""}, {"name": "Content-Type", "value": "text/javascript"}, {"name": "Content-Encoding", "value": "br"}, {"name": "Server", "value": "UploadServer"}, {"name": "Via", "value": "1.1 varnish, 1.1 varnish"}, {"name": "Accept-Ranges", "value": "bytes"}, {"name": "Date", "value": "Sun, 17 Oct 2021 18:05:47 GMT"}, {"name": "Age", "value": "5362734"}, {"name": "X-Served-By", "value": "cache-bwi5129-BWI, cache-sea4457-SEA"}, {"name": "X-Cache", "value": "HIT, HIT"}, {"name": "X-Cache-Hits", "value": "1, 50939"}, {"name": "X-Timer", "value": "S1634493947.229104,VS0,VE0"}, {"name": "Vary", "value": "Accept-Encoding"}, {"name": "Access-Control-Allow-Methods", "value": "GET, OPTIONS"}, {"name": "Access-Control-Allow-Origin", "value": "*"}], "content": {"size": 0, "mimeType": "text/javascript", "comment": ""}, "redirectURL": "", "headersSize": 646, "bodySize": 67156, "comment": ""}, "cache": {}, "timings": {"comment": "", "wait": 27, "send": 0, "dns": -1, "ssl": -1, "connect": -1, "blocked": -1, "receive": 43}, "serverIPAddress": "151.101.52.237", "comment": "", "time": 71}, {"pageref": "Duane Hall", "startedDateTime": "2021-10-17T12:05:46.932-06:00", "request": {"method": "GET", "url": "https://assets.squarespace.com/universal/scripts-compressed/common-vendors-b4cd0ebd7fbdd0888c6f1-min.en-US.js", "httpVersion": "HTTP/1.1", "cookies": [], "headers": [{"name": "Host", "value": "assets.squarespace.com"}, {"name": "User-Agent", "value": "Mozilla/5.0 (Windows NT 10.0; Win64; x64; rv:93.0) Gecko/20100101 Firefox/93.0"}, {"name": "Accept", "value": "*/*"}, {"name": "Accept-Language", "value": "en-US,en;q=0.5"}, {"name": "Accept-Encoding", "value": "gzip, deflate, br"}, {"name": "Origin", "value": "https://www.voteforhallward6.ca"}, {"name": "Connection", "value": "keep-alive"}, {"name": "Referer", "value": "https://www.voteforhallward6.ca/"}, {"name": "Sec-Fetch-Dest", "value": "script"}, {"name": "Sec-Fetch-Mode", "value": "cors"}, {"name": "Sec-Fetch-Site", "value": "cross-site"}], "queryString": [], "headersSize": 484, "bodySize": 0, "comment": ""}, "response": {"status": 200, "statusText": "OK", "httpVersion": "HTTP/1.1", "cookies": [], "headers": [{"name": "Connection", "value": "keep-alive"}, {"name": "Content-Length", "value": "149093"}, {"name": "Cache-Control", "value": "public, max-age=31536000"}, {"name": "Expires", "value": "Fri, 14 Oct 2022 18:59:08 GMT"}, {"name": "Last-Modified", "value": "Thu, 14 Oct 2021 18:08:39 GMT"}, {"name": "ETag", "value": "\"50f6071a5ddb77744bb80e6238ab4654\""}, {"name": "Content-Type", "value": "text/javascript"}, {"name": "Content-Encoding", "value": "br"}, {"name": "Server", "value": "UploadServer"}, {"name": "Via", "value": "1.1 varnish, 1.1 varnish"}, {"name": "Accept-Ranges", "value": "bytes"}, {"name": "Date", "value": "Sun, 17 Oct 2021 18:05:47 GMT"}, {"name": "Age", "value": "255999"}, {"name": "X-Served-By", "value": "cache-bwi5175-BWI, cache-sea4443-SEA"}, {"name": "X-Cache", "value": "MISS, HIT"}, {"name": "X-Cache-Hits", "value": "0, 5"}, {"name": "X-Timer", "value": "S1634493947.231073,VS0,VE0"}, {"name": "Vary", "value": "Accept-Encoding"}, {"name": "Access-Control-Allow-Methods", "value": "GET, OPTIONS"}, {"name": "Access-Control-Allow-Origin", "value": "*"}], "content": {"size": 0, "mimeType": "text/javascript", "comment": ""}, "redirectURL": "", "headersSize": 643, "bodySize": 149093, "comment": ""}, "cache": {}, "timings": {"comment": "", "wait": 37, "send": 0, "dns": -1, "ssl": -1, "connect": -1, "blocked": -1, "receive": 63}, "serverIPAddress": "151.101.52.237", "comment": "", "time": 101}, {"pageref": "Duane Hall", "startedDateTime": "2021-10-17T12:05:46.932-06:00", "request": {"method": "GET", "url": "https://static1.squarespace.com/static/versioned-site-css/6146688be7110b3c5077b4dc/2/5c5a519771c10ba3470d8101/6146688be7110b3c5077b4f6/1126/site.css", "httpVersion": "HTTP/1.1", "cookies": [], "headers": [{"name": "Host", "value": "static1.squarespace.com"}, {"name": "User-Agent", "value": "Mozilla/5.0 (Windows NT 10.0; Win64; x64; rv:93.0) Gecko/20100101 Firefox/93.0"}, {"name": "Accept", "value": "text/css,*/*;q=0.1"}, {"name": "Accept-Language", "value": "en-US,en;q=0.5"}, {"name": "Accept-Encoding", "value": "gzip, deflate, br"}, {"name": "Connection", "value": "keep-alive"}, {"name": "Referer", "value": "https://www.voteforhallward6.ca/"}, {"name": "Sec-Fetch-Dest", "value": "style"}, {"name": "Sec-Fetch-Mode", "value": "no-cors"}, {"name": "Sec-Fetch-Site", "value": "cross-site"}], "queryString": [], "headersSize": 499, "bodySize": 0, "comment": ""}, "response": {"status": 200, "statusText": "OK", "httpVersion": "HTTP/1.1", "cookies": [], "headers": [{"name": "Connection", "value": "keep-alive"}, {"name": "Content-Length", "value": "84792"}, {"name": "Cache-Control", "value": "public, max-age=94608000"}, {"name": "Content-Encoding", "value": "gzip"}, {"name": "Content-Type", "value": "text/css; charset=UTF-8"}, {"name": "Pragma", "value": "cache"}, {"name": "Server", "value": "Squarespace"}, {"name": "Timing-Allow-Origin", "value": "*"}, {"name": "X-Content-Type-Options", "value": "nosniff"}, {"name": "X-Contextid", "value": "5xLK7ipP/Qtia29Er"}, {"name": "Via", "value": "1.1 varnish, 1.1 varnish"}, {"name": "Accept-Ranges", "value": "bytes"}, {"name": "Date", "value": "Sun, 17 Oct 2021 18:05:47 GMT"}, {"name": "Age", "value": "152902"}, {"name": "X-Served-By", "value": "cache-dfw18659-DFW, cache-sea4445-SEA"}, {"name": "X-Cache", "value": "HIT, HIT"}, {"name": "X-Cache-Hits", "value": "1, 1"}, {"name": "X-Timer", "value": "S1634493947.229517,VS0,VE1"}, {"name": "Vary", "value": "Accept-Encoding"}, {"name": "Tracepoint", "value": "Fastly"}], "content": {"size": 0, "mimeType": "text/css; charset=UTF-8", "comment": ""}, "redirectURL": "", "headersSize": 571, "bodySize": 84792, "comment": ""}, "cache": {}, "timings": {"comment": "", "wait": 25, "send": 0, "dns": -1, "ssl": -1, "connect": -1, "blocked": -1, "receive": 21}, "serverIPAddress": "151.101.52.238", "comment": "", "time": 46}, {"pageref": "Duane Hall", "startedDateTime": "2021-10-17T12:05:46.947-06:00", "request": {"method": "GET", "url": "https://assets.squarespace.com/universal/scripts-compressed/common-0d88c3401f258fdacb205-min.en-US.js", "httpVersion": "HTTP/1.1", "cookies": [], "headers": [{"name": "Host", "value": "assets.squarespace.com"}, {"name": "User-Agent", "value": "Mozilla/5.0 (Windows NT 10.0; Win64; x64; rv:93.0) Gecko/20100101 Firefox/93.0"}, {"name": "Accept", "value": "*/*"}, {"name": "Accept-Language", "value": "en-US,en;q=0.5"}, {"name": "Accept-Encoding", "value": "gzip, deflate, br"}, {"name": "Origin", "value": "https://www.voteforhallward6.ca"}, {"name": "Connection", "value": "keep-alive"}, {"name": "Referer", "value": "https://www.voteforhallward6.ca/"}, {"name": "Sec-Fetch-Dest", "value": "script"}, {"name": "Sec-Fetch-Mode", "value": "cors"}, {"name": "Sec-Fetch-Site", "value": "cross-site"}], "queryString": [], "headersSize": 476, "bodySize": 0, "comment": ""}, "response": {"status": 200, "statusText": "OK", "httpVersion": "HTTP/1.1", "cookies": [], "headers": [{"name": "Connection", "value": "keep-alive"}, {"name": "Content-Length", "value": "163499"}, {"name": "Cache-Control", "value": "public, max-age=31536000"}, {"name": "Expires", "value": "Sat, 15 Oct 2022 20:37:25 GMT"}, {"name": "Last-Modified", "value": "Fri, 15 Oct 2021 18:21:03 GMT"}, {"name": "ETag", "value": "\"fc3800c6249b086ce662b3958f175fbc\""}, {"name": "Content-Type", "value": "text/javascript"}, {"name": "Content-Encoding", "value": "br"}, {"name": "Server", "value": "UploadServer"}, {"name": "Via", "value": "1.1 varnish, 1.1 varnish"}, {"name": "Accept-Ranges", "value": "bytes"}, {"name": "Date", "value": "Sun, 17 Oct 2021 18:05:47 GMT"}, {"name": "Age", "value": "163701"}, {"name": "X-Served-By", "value": "cache-bwi5163-BWI, cache-sea4437-SEA"}, {"name": "X-Cache", "value": "HIT, HIT"}, {"name": "X-Cache-Hits", "value": "1, 1"}, {"name": "X-Timer", "value": "S1634493947.232582,VS0,VE1"}, {"name": "Vary", "value": "Accept-Encoding"}, {"name": "Access-Control-Allow-Methods", "value": "GET, OPTIONS"}, {"name": "Access-Control-Allow-Origin", "value": "*"}], "content": {"size": 0, "mimeType": "text/javascript", "comment": ""}, "redirectURL": "", "headersSize": 642, "bodySize": 163499, "comment": ""}, "cache": {}, "timings": {"comment": "", "wait": 30, "send": 0, "dns": -1, "ssl": -1, "connect": -1, "blocked": -1, "receive": 79}, "serverIPAddress": "151.101.52.237", "comment": "", "time": 110}, {"pageref": "Duane Hall", "startedDateTime": "2021-10-17T12:05:46.947-06:00", "request": {"method": "GET", "url": "https://static1.squarespace.com/static/vta/5c5a519771c10ba3470d8101/scripts/site-bundle.e0a75d11d48805853dfaa9069b6a74aa.js", "httpVersion": "HTTP/1.1", "cookies": [], "headers": [{"name": "Host", "value": "static1.squarespace.com"}, {"name": "User-Agent", "value": "Mozilla/5.0 (Windows NT 10.0; Win64; x64; rv:93.0) Gecko/20100101 Firefox/93.0"}, {"name": "Accept", "value": "*/*"}, {"name": "Accept-Language", "value": "en-US,en;q=0.5"}, {"name": "Accept-Encoding", "value": "gzip, deflate, br"}, {"name": "Connection", "value": "keep-alive"}, {"name": "Referer", "value": "https://www.voteforhallward6.ca/"}, {"name": "Sec-Fetch-Dest", "value": "script"}, {"name": "Sec-Fetch-Mode", "value": "no-cors"}, {"name": "Sec-Fetch-Site", "value": "cross-site"}], "queryString": [], "headersSize": 460, "bodySize": 0, "comment": ""}, "response": {"status": 200, "statusText": "OK", "httpVersion": "HTTP/1.1", "cookies": [], "headers": [{"name": "Connection", "value": "keep-alive"}, {"name": "Content-Length", "value": "38230"}, {"name": "Cache-Control", "value": "public, max-age=94608000"}, {"name": "Content-Encoding", "value": "gzip"}, {"name": "Content-Type", "value": "application/javascript; charset=UTF-8"}, {"name": "Pragma", "value": "cache"}, {"name": "Server", "value": "Squarespace"}, {"name": "Timing-Allow-Origin", "value": "*"}, {"name": "X-Content-Type-Options", "value": "nosniff"}, {"name": "X-Contextid", "value": "JO4EvvxJ/17bvFnuW"}, {"name": "Via", "value": "1.1 varnish, 1.1 varnish"}, {"name": "Accept-Ranges", "value": "bytes"}, {"name": "Date", "value": "Sun, 17 Oct 2021 18:05:47 GMT"}, {"name": "Age", "value": "512184"}, {"name": "X-Served-By", "value": "cache-dfw18623-DFW, cache-sea4455-SEA"}, {"name": "X-Cache", "value": "HIT, HIT"}, {"name": "X-Cache-Hits", "value": "1, 21119"}, {"name": "X-Timer", "value": "S1634493947.242129,VS0,VE0"}, {"name": "Vary", "value": "Accept-Encoding"}, {"name": "Tracepoint", "value": "Fastly"}], "content": {"size": 0, "mimeType": "application/javascript; charset=UTF-8", "comment": ""}, "redirectURL": "", "headersSize": 589, "bodySize": 38230, "comment": ""}, "cache": {}, "timings": {"comment": "", "wait": 42, "send": 0, "dns": -1, "ssl": -1, "connect": -1, "blocked": -1, "receive": 14}, "serverIPAddress": "151.101.52.238", "comment": "", "time": 56}, {"pageref": "Duane Hall", "startedDateTime": "2021-10-17T12:05:46.963-06:00", "request": {"method": "GET", "url": "https://assets.squarespace.com/universal/scripts-compressed/performance-f5c05a45c62741fccc406-min.en-US.js", "httpVersion": "HTTP/1.1", "cookies": [], "headers": [{"name": "Host", "value": "assets.squarespace.com"}, {"name": "User-Agent", "value": "Mozilla/5.0 (Windows NT 10.0; Win64; x64; rv:93.0) Gecko/20100101 Firefox/93.0"}, {"name": "Accept", "value": "*/*"}, {"name": "Accept-Language", "value": "en-US,en;q=0.5"}, {"name": "Accept-Encoding", "value": "gzip, deflate, br"}, {"name": "Origin", "value": "https://www.voteforhallward6.ca"}, {"name": "Connection", "value": "keep-alive"}, {"name": "Referer", "value": "https://www.voteforhallward6.ca/"}, {"name": "Sec-Fetch-Dest", "value": "script"}, {"name": "Sec-Fetch-Mode", "value": "cors"}, {"name": "Sec-Fetch-Site", "value": "cross-site"}], "queryString": [], "headersSize": 481, "bodySize": 0, "comment": ""}, "response": {"status": 200, "statusText": "OK", "httpVersion": "HTTP/1.1", "cookies": [], "headers": [{"name": "Connection", "value": "keep-alive"}, {"name": "Content-Length", "value": "11924"}, {"name": "Cache-Control", "value": "public, max-age=31536000"}, {"name": "Expires", "value": "Sat, 15 Oct 2022 01:00:44 GMT"}, {"name": "Last-Modified", "value": "Thu, 14 Oct 2021 23:57:34 GMT"}, {"name": "ETag", "value": "\"d8dfba4aa37094f483686a3052e10977\""}, {"name": "Content-Type", "value": "text/javascript"}, {"name": "Content-Encoding", "value": "br"}, {"name": "Server", "value": "UploadServer"}, {"name": "Via", "value": "1.1 varnish, 1.1 varnish"}, {"name": "Accept-Ranges", "value": "bytes"}, {"name": "Date", "value": "Sun, 17 Oct 2021 18:05:47 GMT"}, {"name": "Age", "value": "234305"}, {"name": "X-Served-By", "value": "cache-bwi5136-BWI, cache-sea4434-SEA"}, {"name": "X-Cache", "value": "HIT, HIT"}, {"name": "X-Cache-Hits", "value": "3, 26250"}, {"name": "X-Timer", "value": "S1634493947.279067,VS0,VE0"}, {"name": "Vary", "value": "Accept-Encoding"}, {"name": "Access-Control-Allow-Methods", "value": "GET, OPTIONS"}, {"name": "Access-Control-Allow-Origin", "value": "*"}], "content": {"size": 0, "mimeType": "text/javascript", "comment": ""}, "redirectURL": "", "headersSize": 645, "bodySize": 11924, "comment": ""}, "cache": {}, "timings": {"comment": "", "wait": 37, "send": 0, "dns": -1, "ssl": -1, "connect": -1, "blocked": -1, "receive": 7}, "serverIPAddress": "151.101.52.237", "comment": "", "time": 45}, {"pageref": "Duane Hall", "startedDateTime": "2021-10-17T12:05:47.079-06:00", "request": {"method": "GET", "url": "https://use.typekit.net/ik/mgrkVD7gotOX9mElmcIrpDJFDvyKhMxjtiDxv-gjAV3fe7tIfFHN4UJLFRbh52jhWDjUF2jh52yKZQSUwQgKwhwuw2SajRsqjU7cMkG0jAFu-WsoShFGZAsude80ZkoRdhXCHKoyjamTiY8Djhy8ZYmC-Ao1Oco8if37OcBDOcu8OfG0ja4TdWFzdKuljW8cdeNaZWJlZ1gK-KoDSWmyScmDSeBRZPoRdhXCHKoDSWmyScmDSeBRZWFR-emqiAUTdcS0jhNlOeBRiA8XpWFR-emqiAUTdcS0jhNlOeBRiA8XpWFR-emqiAUTdcS0dcmXOeBDOcu8OeFk-AuDdhtldABoZcUzihmkOAZ3jcG0SaBujW48Sagyjh90jhNlOeUzjhBC-eNDifUDSWmyScmDSeBRZWFR-emqiAUTdcS0jhNlOYZziemcda4GjAUCihBkZ2j0jhICiaiaOcBRiA8XpWFR-emqiAUTdcS0jhNlOYiaikoyjamTiY8Djhy8ZYmC-Ao1Oco8ifUaiaS0jWw0dA9CiaiaOcFk-AuDdhtldABoZcUzihmkOAZ3jcG0SaBujW48Sagyjh90jhNlOYiaikoDSWmyScmDSeBRZWFR-emqiAUTdcS0jhNlOYiaikohdas8ZcNk-eBCdYiyScbhOcFyJ6TnZWgCZWJlSasqH6qJq9XbMg62JMJ7fbKFQsMMeMb6MKG4f44FIMMjgPMfH6qJRXXbMg6YJMJ7fbKJSyMMeMX6MKG4fJoFIMMj2KMfH6qJqIXbMg6sJMHbM-AU1jGe.js", "httpVersion": "HTTP/1.1", "cookies": [], "headers": [{"name": "Host", "value": "use.typekit.net"}, {"name": "User-Agent", "value": "Mozilla/5.0 (Windows NT 10.0; Win64; x64; rv:93.0) Gecko/20100101 Firefox/93.0"}, {"name": "Accept", "value": "*/*"}, {"name": "Accept-Language", "value": "en-US,en;q=0.5"}, {"name": "Accept-Encoding", "value": "gzip, deflate, br"}, {"name": "Connection", "value": "keep-alive"}, {"name": "Referer", "value": "https://www.voteforhallward6.ca/"}, {"name": "Sec-Fetch-Dest", "value": "script"}, {"name": "Sec-Fetch-Mode", "value": "no-cors"}, {"name": "Sec-Fetch-Site", "value": "cross-site"}], "queryString": [], "headersSize": 1159, "bodySize": 0, "comment": ""}, "response": {"status": 200, "statusText": "OK", "httpVersion": "HTTP/1.1", "cookies": [], "headers": [{"name": "Access-Control-Allow-Origin", "value": "*"}, {"name": "Cache-Control", "value": "public, max-age=604800"}, {"name": "Content-Encoding", "value": "gzip"}, {"name": "Content-Type", "value": "text/javascript;charset=utf-8"}, {"name": "Cross-Origin-Resource-Policy", "value": "cross-origin"}, {"name": "Server", "value": "nginx"}, {"name": "Strict-Transport-Security", "value": "max-age=31536000; includeSubDomains;"}, {"name": "Timing-Allow-Origin", "value": "*"}, {"name": "Vary", "value": "Accept-Encoding"}, {"name": "Content-Length", "value": "6945"}, {"name": "Date", "value": "Sun, 17 Oct 2021 18:05:47 GMT"}, {"name": "Connection", "value": "keep-alive"}], "content": {"size": 0, "mimeType": "text/javascript;charset=utf-8", "comment": ""}, "redirectURL": "", "headersSize": 415, "bodySize": 6945, "comment": ""}, "cache": {}, "timings": {"comment": "", "wait": 20, "send": 0, "dns": 4, "ssl": 119, "connect": 140, "blocked": 0, "receive": 0}, "serverIPAddress": "23.59.154.19", "comment": "", "time": 165}, {"pageref": "Duane Hall", "startedDateTime": "2021-10-17T12:05:47.110-06:00", "request": {"method": "GET", "url": "https://images.squarespace-cdn.com/content/v1/6146688be7110b3c5077b4dc/4b10f0af-b319-4764-bb0c-d34bf91b8311/logo_200x200.jpg?format=1500w", "httpVersion": "HTTP/1.1", "cookies": [], "headers": [{"name": "Host", "value": "images.squarespace-cdn.com"}, {"name": "User-Agent", "value": "Mozilla/5.0 (Windows NT 10.0; Win64; x64; rv:93.0) Gecko/20100101 Firefox/93.0"}, {"name": "Accept", "value": "image/avif,image/webp,*/*"}, {"name": "Accept-Language", "value": "en-US,en;q=0.5"}, {"name": "Accept-Encoding", "value": "gzip, deflate, br"}, {"name": "Connection", "value": "keep-alive"}, {"name": "Referer", "value": "https://www.voteforhallward6.ca/"}, {"name": "Sec-Fetch-Dest", "value": "image"}, {"name": "Sec-Fetch-Mode", "value": "no-cors"}, {"name": "Sec-Fetch-Site", "value": "cross-site"}], "queryString": [{"name": "format", "value": "1500w"}], "headersSize": 495, "bodySize": 0, "comment": ""}, "response": {"status": 200, "statusText": "OK", "httpVersion": "HTTP/1.1", "cookies": [], "headers": [{"name": "Connection", "value": "keep-alive"}, {"name": "Content-Length", "value": "6320"}, {"name": "Timing-allow-origin", "value": "*"}, {"name": "Access-control-expose-headers", "value": "Content-Length, Timing-Allow-Origin"}, {"name": "Content-type", "value": "image/jpeg"}, {"name": "Access-control-allow-origin", "value": "*"}, {"name": "Etag", "value": "CPDtoMqYivMCEAE="}, {"name": "Cache-control", "value": "max-age=604800"}, {"name": "Via", "value": "1.1 google, 1.1 varnish, 1.1 varnish"}, {"name": "Accept-Ranges", "value": "bytes"}, {"name": "Date", "value": "Sun, 17 Oct 2021 18:05:47 GMT"}, {"name": "Age", "value": "264038"}, {"name": "X-Served-By", "value": "cache-bwi5124-BWI, cache-sea4425-SEA"}, {"name": "X-Cache", "value": "HIT, HIT"}, {"name": "X-Cache-Hits", "value": "1, 1"}, {"name": "X-Timer", "value": "S1634493947.416248,VS0,VE1"}, {"name": "Vary", "value": "Accept-Encoding"}, {"name": "Tracepoint", "value": "Fastly"}], "content": {"size": 0, "mimeType": "image/jpeg", "comment": ""}, "redirectURL": "", "headersSize": 557, "bodySize": 6320, "comment": ""}, "cache": {}, "timings": {"comment": "", "wait": 39, "send": 0, "dns": -1, "ssl": -1, "connect": -1, "blocked": -1, "receive": 2}, "serverIPAddress": "151.101.52.238", "comment": "", "time": 42}, {"pageref": "Duane Hall", "startedDateTime": "2021-10-17T12:05:47.195-06:00", "request": {"method": "GET", "url": "https://use.typekit.net/af/b795d0/000000000000000000013142/27/l?subset_id=2&fvd=n3&v=3", "httpVersion": "HTTP/1.1", "cookies": [], "headers": [{"name": "Host", "value": "use.typekit.net"}, {"name": "User-Agent", "value": "Mozilla/5.0 (Windows NT 10.0; Win64; x64; rv:93.0) Gecko/20100101 Firefox/93.0"}, {"name": "Accept", "value": "application/font-woff2;q=1.0,application/font-woff;q=0.9,*/*;q=0.8"}, {"name": "Accept-Language", "value": "en-US,en;q=0.5"}, {"name": "Accept-Encoding", "value": "identity"}, {"name": "Origin", "value": "https://www.voteforhallward6.ca"}, {"name": "Connection", "value": "keep-alive"}, {"name": "Referer", "value": "https://www.voteforhallward6.ca/"}, {"name": "Sec-Fetch-Dest", "value": "font"}, {"name": "Sec-Fetch-Mode", "value": "cors"}, {"name": "Sec-Fetch-Site", "value": "cross-site"}], "queryString": [{"name": "subset_id", "value": "2"}, {"name": "fvd", "value": "n3"}, {"name": "v", "value": "3"}], "headersSize": 513, "bodySize": 0, "comment": ""}, "response": {"status": 200, "statusText": "OK", "httpVersion": "HTTP/1.1", "cookies": [], "headers": [{"name": "Access-Control-Allow-Origin", "value": "*"}, {"name": "Cache-Control", "value": "public, max-age=31536000"}, {"name": "Content-Type", "value": "application/font-woff2"}, {"name": "Cross-Origin-Resource-Policy", "value": "cross-origin"}, {"name": "ETag", "value": "\"3d3c1778e8ee1d17a43b257fa9d28851838e4db3\""}, {"name": "Server", "value": "nginx"}, {"name": "Timing-Allow-Origin", "value": "*"}, {"name": "Content-Length", "value": "28696"}, {"name": "Date", "value": "Sun, 17 Oct 2021 18:05:47 GMT"}, {"name": "Connection", "value": "keep-alive"}], "content": {"size": 0, "mimeType": "application/font-woff2", "comment": ""}, "redirectURL": "", "headersSize": 349, "bodySize": 28696, "comment": ""}, "cache": {}, "timings": {"comment": "", "wait": 25, "send": 0, "dns": 0, "ssl": 56, "connect": 74, "blocked": 0, "receive": 1}, "serverIPAddress": "23.59.154.19", "comment": "", "time": 102}, {"pageref": "Duane Hall", "startedDateTime": "2021-10-17T12:05:47.210-06:00", "request": {"method": "GET", "url": "https://use.typekit.net/af/4337b5/000000000000000000013144/27/l?subset_id=2&fvd=n5&v=3", "httpVersion": "HTTP/1.1", "cookies": [], "headers": [{"name": "Host", "value": "use.typekit.net"}, {"name": "User-Agent", "value": "Mozilla/5.0 (Windows NT 10.0; Win64; x64; rv:93.0) Gecko/20100101 Firefox/93.0"}, {"name": "Accept", "value": "application/font-woff2;q=1.0,application/font-woff;q=0.9,*/*;q=0.8"}, {"name": "Accept-Language", "value": "en-US,en;q=0.5"}, {"name": "Accept-Encoding", "value": "identity"}, {"name": "Origin", "value": "https://www.voteforhallward6.ca"}, {"name": "Connection", "value": "keep-alive"}, {"name": "Referer", "value": "https://www.voteforhallward6.ca/"}, {"name": "Sec-Fetch-Dest", "value": "font"}, {"name": "Sec-Fetch-Mode", "value": "cors"}, {"name": "Sec-Fetch-Site", "value": "cross-site"}], "queryString": [{"name": "subset_id", "value": "2"}, {"name": "fvd", "value": "n5"}, {"name": "v", "value": "3"}], "headersSize": 513, "bodySize": 0, "comment": ""}, "response": {"status": 200, "statusText": "OK", "httpVersion": "HTTP/1.1", "cookies": [], "headers": [{"name": "Access-Control-Allow-Origin", "value": "*"}, {"name": "Cache-Control", "value": "public, max-age=31536000"}, {"name": "Content-Type", "value": "application/font-woff2"}, {"name": "Cross-Origin-Resource-Policy", "value": "cross-origin"}, {"name": "ETag", "value": "\"9707effc518ff42f9b7a5479fd118907a2a67908\""}, {"name": "Server", "value": "nginx"}, {"name": "Timing-Allow-Origin", "value": "*"}, {"name": "Content-Length", "value": "28700"}, {"name": "Date", "value": "Sun, 17 Oct 2021 18:05:47 GMT"}, {"name": "Connection", "value": "keep-alive"}], "content": {"size": 0, "mimeType": "application/font-woff2", "comment": ""}, "redirectURL": "", "headersSize": 349, "bodySize": 28700, "comment": ""}, "cache": {}, "timings": {"comment": "", "wait": 26, "send": 0, "dns": 0, "ssl": 60, "connect": 76, "blocked": 0, "receive": 2}, "serverIPAddress": "23.59.154.19", "comment": "", "time": 106}, {"pageref": "Duane Hall", "startedDateTime": "2021-10-17T12:05:47.210-06:00", "request": {"method": "GET", "url": "https://www.voteforhallward6.ca/api/1/performance/settings", "httpVersion": "HTTP/1.1", "cookies": [], "headers": [{"name": "Host", "value": "www.voteforhallward6.ca"}, {"name": "User-Agent", "value": "Mozilla/5.0 (Windows NT 10.0; Win64; x64; rv:93.0) Gecko/20100101 Firefox/93.0"}, {"name": "Accept", "value": "*/*"}, {"name": "Accept-Language", "value": "en-US,en;q=0.5"}, {"name": "Accept-Encoding", "value": "gzip, deflate, br"}, {"name": "Connection", "value": "keep-alive"}, {"name": "Referer", "value": "https://www.voteforhallward6.ca/"}, {"name": "Cookie", "value": "crumb=BTDwk43FTzXnNzFmM2IzMTg4OTA5NzNkNTQyYjJlYmQzOGM5NmVh"}, {"name": "Sec-Fetch-Dest", "value": "empty"}, {"name": "Sec-Fetch-Mode", "value": "cors"}, {"name": "Sec-Fetch-Site", "value": "same-origin"}], "queryString": [], "headersSize": 460, "bodySize": 0, "comment": ""}, "response": {"status": 200, "statusText": "OK", "httpVersion": "HTTP/1.1", "cookies": [], "headers": [{"name": "Content-Encoding", "value": "gzip"}, {"name": "Content-Length", "value": "429"}, {"name": "Content-Type", "value": "application/json"}, {"name": "Date", "value": "Sun, 17 Oct 2021 18:05:47 GMT"}, {"name": "Server", "value": "Squarespace"}, {"name": "Vary", "value": "Accept-Encoding, User-Agent"}, {"name": "X-Contextid", "value": "FQR9dZRM/NOJFO7gs"}], "content": {"size": 0, "mimeType": "application/json", "comment": ""}, "redirectURL": "", "headersSize": 223, "bodySize": 429, "comment": ""}, "cache": {}, "timings": {"comment": "", "wait": 58, "send": 0, "dns": -1, "ssl": -1, "connect": -1, "blocked": -1, "receive": 0}, "serverIPAddress": "198.185.159.145", "comment": "", "time": 59}, {"pageref": "Duane Hall", "startedDateTime": "2021-10-17T12:05:47.210-06:00", "request": {"method": "GET", "url": "https://static1.squarespace.com/static/vta/5c5a519771c10ba3470d8101/scripts/floating-cart.abd5bddcd8ef5f33274c.js", "httpVersion": "HTTP/1.1", "cookies": [], "headers": [{"name": "Host", "value": "static1.squarespace.com"}, {"name": "User-Agent", "value": "Mozilla/5.0 (Windows NT 10.0; Win64; x64; rv:93.0) Gecko/20100101 Firefox/93.0"}, {"name": "Accept", "value": "*/*"}, {"name": "Accept-Language", "value": "en-US,en;q=0.5"}, {"name": "Accept-Encoding", "value": "gzip, deflate, br"}, {"name": "Connection", "value": "keep-alive"}, {"name": "Referer", "value": "https://www.voteforhallward6.ca/"}, {"name": "Sec-Fetch-Dest", "value": "script"}, {"name": "Sec-Fetch-Mode", "value": "no-cors"}, {"name": "Sec-Fetch-Site", "value": "cross-site"}], "queryString": [], "headersSize": 450, "bodySize": 0, "comment": ""}, "response": {"status": 200, "statusText": "OK", "httpVersion": "HTTP/1.1", "cookies": [], "headers": [{"name": "Connection", "value": "keep-alive"}, {"name": "Content-Length", "value": "310"}, {"name": "Cache-Control", "value": "public, max-age=94608000"}, {"name": "Content-Encoding", "value": "gzip"}, {"name": "Content-Type", "value": "application/javascript; charset=UTF-8"}, {"name": "Pragma", "value": "cache"}, {"name": "Server", "value": "Squarespace"}, {"name": "Timing-Allow-Origin", "value": "*"}, {"name": "X-Content-Type-Options", "value": "nosniff"}, {"name": "X-Contextid", "value": "FqE4guiG/1lBilA0F"}, {"name": "Via", "value": "1.1 varnish, 1.1 varnish"}, {"name": "Accept-Ranges", "value": "bytes"}, {"name": "Date", "value": "Sun, 17 Oct 2021 18:05:47 GMT"}, {"name": "Age", "value": "512184"}, {"name": "X-Served-By", "value": "cache-dfw18624-DFW, cache-sea4445-SEA"}, {"name": "X-Cache", "value": "MISS, HIT"}, {"name": "X-Cache-Hits", "value": "0, 9833"}, {"name": "X-Timer", "value": "S1634493948.505749,VS0,VE0"}, {"name": "Vary", "value": "Accept-Encoding"}, {"name": "Tracepoint", "value": "Fastly"}], "content": {"size": 0, "mimeType": "application/javascript; charset=UTF-8", "comment": ""}, "redirectURL": "", "headersSize": 587, "bodySize": 310, "comment": ""}, "cache": {}, "timings": {"comment": "", "wait": 20, "send": 0, "dns": -1, "ssl": -1, "connect": -1, "blocked": -1, "receive": 0}, "serverIPAddress": "151.101.52.238", "comment": "", "time": 20}, {"pageref": "Duane Hall", "startedDateTime": "2021-10-17T12:05:47.233-06:00", "request": {"method": "GET", "url": "https://use.typekit.net/af/2c86cd/000000000000000000013140/27/l?subset_id=2&fvd=i7&v=3", "httpVersion": "HTTP/1.1", "cookies": [], "headers": [{"name": "Host", "value": "use.typekit.net"}, {"name": "User-Agent", "value": "Mozilla/5.0 (Windows NT 10.0; Win64; x64; rv:93.0) Gecko/20100101 Firefox/93.0"}, {"name": "Accept", "value": "application/font-woff2;q=1.0,application/font-woff;q=0.9,*/*;q=0.8"}, {"name": "Accept-Language", "value": "en-US,en;q=0.5"}, {"name": "Accept-Encoding", "value": "identity"}, {"name": "Origin", "value": "https://www.voteforhallward6.ca"}, {"name": "Connection", "value": "keep-alive"}, {"name": "Referer", "value": "https://www.voteforhallward6.ca/"}, {"name": "Sec-Fetch-Dest", "value": "font"}, {"name": "Sec-Fetch-Mode", "value": "cors"}, {"name": "Sec-Fetch-Site", "value": "cross-site"}], "queryString": [{"name": "subset_id", "value": "2"}, {"name": "fvd", "value": "i7"}, {"name": "v", "value": "3"}], "headersSize": 513, "bodySize": 0, "comment": ""}, "response": {"status": 200, "statusText": "OK", "httpVersion": "HTTP/1.1", "cookies": [], "headers": [{"name": "Access-Control-Allow-Origin", "value": "*"}, {"name": "Cache-Control", "value": "public, max-age=31536000"}, {"name": "Content-Type", "value": "application/font-woff2"}, {"name": "Cross-Origin-Resource-Policy", "value": "cross-origin"}, {"name": "ETag", "value": "\"4237ecdc79f45cb1ce428b9dd9ed0951e1c5fd73\""}, {"name": "Server", "value": "nginx"}, {"name": "Timing-Allow-Origin", "value": "*"}, {"name": "Content-Length", "value": "29112"}, {"name": "Date", "value": "Sun, 17 Oct 2021 18:05:47 GMT"}, {"name": "Connection", "value": "keep-alive"}], "content": {"size": 0, "mimeType": "application/font-woff2", "comment": ""}, "redirectURL": "", "headersSize": 349, "bodySize": 29112, "comment": ""}, "cache": {}, "timings": {"comment": "", "wait": 19, "send": 0, "dns": -1, "ssl": -1, "connect": -1, "blocked": -1, "receive": 1}, "serverIPAddress": "23.59.154.19", "comment": "", "time": 21}, {"pageref": "Duane Hall", "startedDateTime": "2021-10-17T12:05:47.264-06:00", "request": {"method": "GET", "url": "https://use.typekit.net/af/de0ac1/000000000000000000013146/27/l?subset_id=2&fvd=n4&v=3", "httpVersion": "HTTP/1.1", "cookies": [], "headers": [{"name": "Host", "value": "use.typekit.net"}, {"name": "User-Agent", "value": "Mozilla/5.0 (Windows NT 10.0; Win64; x64; rv:93.0) Gecko/20100101 Firefox/93.0"}, {"name": "Accept", "value": "application/font-woff2;q=1.0,application/font-woff;q=0.9,*/*;q=0.8"}, {"name": "Accept-Language", "value": "en-US,en;q=0.5"}, {"name": "Accept-Encoding", "value": "identity"}, {"name": "Origin", "value": "https://www.voteforhallward6.ca"}, {"name": "Connection", "value": "keep-alive"}, {"name": "Referer", "value": "https://www.voteforhallward6.ca/"}, {"name": "Sec-Fetch-Dest", "value": "font"}, {"name": "Sec-Fetch-Mode", "value": "cors"}, {"name": "Sec-Fetch-Site", "value": "cross-site"}], "queryString": [{"name": "subset_id", "value": "2"}, {"name": "fvd", "value": "n4"}, {"name": "v", "value": "3"}], "headersSize": 513, "bodySize": 0, "comment": ""}, "response": {"status": 200, "statusText": "OK", "httpVersion": "HTTP/1.1", "cookies": [], "headers": [{"name": "Access-Control-Allow-Origin", "value": "*"}, {"name": "Cache-Control", "value": "public, max-age=31536000"}, {"name": "Content-Type", "value": "application/font-woff2"}, {"name": "Cross-Origin-Resource-Policy", "value": "cross-origin"}, {"name": "ETag", "value": "\"9d7cf1d175abf95cc21cfcf88475d1e6d542035f\""}, {"name": "Server", "value": "nginx"}, {"name": "Timing-Allow-Origin", "value": "*"}, {"name": "Content-Length", "value": "28660"}, {"name": "Date", "value": "Sun, 17 Oct 2021 18:05:47 GMT"}, {"name": "Connection", "value": "keep-alive"}], "content": {"size": 0, "mimeType": "application/font-woff2", "comment": ""}, "redirectURL": "", "headersSize": 349, "bodySize": 28660, "comment": ""}, "cache": {}, "timings": {"comment": "", "wait": 21, "send": 0, "dns": 0, "ssl": 20, "connect": 38, "blocked": 0, "receive": 1}, "serverIPAddress": "23.59.154.19", "comment": "", "time": 61}, {"pageref": "Duane Hall", "startedDateTime": "2021-10-17T12:05:47.279-06:00", "request": {"method": "POST", "url": "https://www.voteforhallward6.ca/api/census/RecordHit", "httpVersion": "HTTP/1.1", "cookies": [], "headers": [{"name": "Host", "value": "www.voteforhallward6.ca"}, {"name": "User-Agent", "value": "Mozilla/5.0 (Windows NT 10.0; Win64; x64; rv:93.0) Gecko/20100101 Firefox/93.0"}, {"name": "Accept", "value": "application/json, text/plain, */*"}, {"name": "Accept-Language", "value": "en-US,en;q=0.5"}, {"name": "Accept-Encoding", "value": "gzip, deflate, br"}, {"name": "Content-Type", "value": "application/x-www-form-urlencoded; charset=utf-8"}, {"name": "X-CSRF-Token", "value": "BTDwk43FTzXnNzFmM2IzMTg4OTA5NzNkNTQyYjJlYmQzOGM5NmVh"}, {"name": "Content-Length", "value": "781"}, {"name": "Origin", "value": "https://www.voteforhallward6.ca"}, {"name": "Connection", "value": "keep-alive"}, {"name": "Referer", "value": "https://www.voteforhallward6.ca/"}, {"name": "Cookie", "value": "crumb=BTDwk43FTzXnNzFmM2IzMTg4OTA5NzNkNTQyYjJlYmQzOGM5NmVh; ss_cvr=9cb39bce-9228-4402-82ce-8f379af49ad7|1634493947260|1634493947260|1634493947260|1; ss_cvt=1634493947260"}, {"name": "Sec-Fetch-Dest", "value": "empty"}, {"name": "Sec-Fetch-Mode", "value": "cors"}, {"name": "Sec-Fetch-Site", "value": "same-origin"}], "queryString": [], "headersSize": 790, "bodySize": 781, "comment": ""}, "response": {"status": 200, "statusText": "OK", "httpVersion": "HTTP/1.1", "cookies": [], "headers": [{"name": "Cache-Control", "value": "no-cache, no-store, must-revalidate"}, {"name": "Content-Type", "value": "application/json;charset=utf-8"}, {"name": "Date", "value": "Sun, 17 Oct 2021 18:05:47 GMT"}, {"name": "Server", "value": "Squarespace"}, {"name": "Strict-Transport-Security", "value": "max-age=43200"}, {"name": "X-Content-Type-Options", "value": "nosniff"}, {"name": "X-Contextid", "value": "FQR9dZRM/zCa3tR2n"}, {"name": "Content-Length", "value": "17"}], "content": {"size": 0, "mimeType": "application/json;charset=utf-8", "comment": ""}, "redirectURL": "", "headersSize": 304, "bodySize": 17, "comment": ""}, "cache": {}, "timings": {"comment": "", "wait": 96, "send": 0, "dns": -1, "ssl": -1, "connect": -1, "blocked": -1, "receive": 0}, "serverIPAddress": "198.185.159.145", "comment": "", "time": 96}, {"pageref": "Duane Hall", "startedDateTime": "2021-10-17T12:05:47.279-06:00", "request": {"method": "GET", "url": "https://use.typekit.net/af/3f55d3/00000000000000000001313f/27/l?subset_id=2&fvd=n7&v=3", "httpVersion": "HTTP/1.1", "cookies": [], "headers": [{"name": "Host", "value": "use.typekit.net"}, {"name": "User-Agent", "value": "Mozilla/5.0 (Windows NT 10.0; Win64; x64; rv:93.0) Gecko/20100101 Firefox/93.0"}, {"name": "Accept", "value": "application/font-woff2;q=1.0,application/font-woff;q=0.9,*/*;q=0.8"}, {"name": "Accept-Language", "value": "en-US,en;q=0.5"}, {"name": "Accept-Encoding", "value": "identity"}, {"name": "Origin", "value": "https://www.voteforhallward6.ca"}, {"name": "Connection", "value": "keep-alive"}, {"name": "Referer", "value": "https://www.voteforhallward6.ca/"}, {"name": "Sec-Fetch-Dest", "value": "font"}, {"name": "Sec-Fetch-Mode", "value": "cors"}, {"name": "Sec-Fetch-Site", "value": "cross-site"}], "queryString": [{"name": "subset_id", "value": "2"}, {"name": "fvd", "value": "n7"}, {"name": "v", "value": "3"}], "headersSize": 513, "bodySize": 0, "comment": ""}, "response": {"status": 200, "statusText": "OK", "httpVersion": "HTTP/1.1", "cookies": [], "headers": [{"name": "Access-Control-Allow-Origin", "value": "*"}, {"name": "Cache-Control", "value": "public, max-age=31536000"}, {"name": "Content-Type", "value": "application/font-woff2"}, {"name": "Cross-Origin-Resource-Policy", "value": "cross-origin"}, {"name": "ETag", "value": "\"c8e3a5f2a91f7f8bff7150e68dc135cf4be8e197\""}, {"name": "Server", "value": "nginx"}, {"name": "Timing-Allow-Origin", "value": "*"}, {"name": "Content-Length", "value": "28796"}, {"name": "Date", "value": "Sun, 17 Oct 2021 18:05:47 GMT"}, {"name": "Connection", "value": "keep-alive"}], "content": {"size": 0, "mimeType": "application/font-woff2", "comment": ""}, "redirectURL": "", "headersSize": 349, "bodySize": 28796, "comment": ""}, "cache": {}, "timings": {"comment": "", "wait": 21, "send": 0, "dns": 0, "ssl": 25, "connect": 49, "blocked": 0, "receive": 1}, "serverIPAddress": "23.59.154.19", "comment": "", "time": 72}, {"pageref": "Duane Hall", "startedDateTime": "2021-10-17T12:05:47.295-06:00", "request": {"method": "GET", "url": "https://use.typekit.net/af/d0cd82/000000000000000000013141/27/l?subset_id=2&fvd=i4&v=3", "httpVersion": "HTTP/1.1", "cookies": [], "headers": [{"name": "Host", "value": "use.typekit.net"}, {"name": "User-Agent", "value": "Mozilla/5.0 (Windows NT 10.0; Win64; x64; rv:93.0) Gecko/20100101 Firefox/93.0"}, {"name": "Accept", "value": "application/font-woff2;q=1.0,application/font-woff;q=0.9,*/*;q=0.8"}, {"name": "Accept-Language", "value": "en-US,en;q=0.5"}, {"name": "Accept-Encoding", "value": "identity"}, {"name": "Origin", "value": "https://www.voteforhallward6.ca"}, {"name": "Connection", "value": "keep-alive"}, {"name": "Referer", "value": "https://www.voteforhallward6.ca/"}, {"name": "Sec-Fetch-Dest", "value": "font"}, {"name": "Sec-Fetch-Mode", "value": "cors"}, {"name": "Sec-Fetch-Site", "value": "cross-site"}], "queryString": [{"name": "subset_id", "value": "2"}, {"name": "fvd", "value": "i4"}, {"name": "v", "value": "3"}], "headersSize": 513, "bodySize": 0, "comment": ""}, "response": {"status": 200, "statusText": "OK", "httpVersion": "HTTP/1.1", "cookies": [], "headers": [{"name": "Access-Control-Allow-Origin", "value": "*"}, {"name": "Cache-Control", "value": "public, max-age=31536000"}, {"name": "Content-Type", "value": "application/font-woff2"}, {"name": "Cross-Origin-Resource-Policy", "value": "cross-origin"}, {"name": "ETag", "value": "\"2c7c7f116f907411e7e40413c3dbb6be138174de\""}, {"name": "Server", "value": "nginx"}, {"name": "Timing-Allow-Origin", "value": "*"}, {"name": "Content-Length", "value": "28740"}, {"name": "Date", "value": "Sun, 17 Oct 2021 18:05:47 GMT"}, {"name": "Connection", "value": "keep-alive"}], "content": {"size": 0, "mimeType": "application/font-woff2", "comment": ""}, "redirectURL": "", "headersSize": 349, "bodySize": 28740, "comment": ""}, "cache": {}, "timings": {"comment": "", "wait": 23, "send": 0, "dns": 0, "ssl": 34, "connect": 57, "blocked": 0, "receive": 1}, "serverIPAddress": "23.59.154.19", "comment": "", "time": 83}, {"pageref": "Duane Hall", "startedDateTime": "2021-10-17T12:05:47.295-06:00", "request": {"method": "GET", "url": "https://use.typekit.net/af/304385/000000000000000000013143/27/l?subset_id=2&fvd=i3&v=3", "httpVersion": "HTTP/1.1", "cookies": [], "headers": [{"name": "Host", "value": "use.typekit.net"}, {"name": "User-Agent", "value": "Mozilla/5.0 (Windows NT 10.0; Win64; x64; rv:93.0) Gecko/20100101 Firefox/93.0"}, {"name": "Accept", "value": "application/font-woff2;q=1.0,application/font-woff;q=0.9,*/*;q=0.8"}, {"name": "Accept-Language", "value": "en-US,en;q=0.5"}, {"name": "Accept-Encoding", "value": "identity"}, {"name": "Origin", "value": "https://www.voteforhallward6.ca"}, {"name": "Connection", "value": "keep-alive"}, {"name": "Referer", "value": "https://www.voteforhallward6.ca/"}, {"name": "Sec-Fetch-Dest", "value": "font"}, {"name": "Sec-Fetch-Mode", "value": "cors"}, {"name": "Sec-Fetch-Site", "value": "cross-site"}], "queryString": [{"name": "subset_id", "value": "2"}, {"name": "fvd", "value": "i3"}, {"name": "v", "value": "3"}], "headersSize": 513, "bodySize": 0, "comment": ""}, "response": {"status": 200, "statusText": "OK", "httpVersion": "HTTP/1.1", "cookies": [], "headers": [{"name": "Access-Control-Allow-Origin", "value": "*"}, {"name": "Cache-Control", "value": "public, max-age=31536000"}, {"name": "Content-Type", "value": "application/font-woff2"}, {"name": "Cross-Origin-Resource-Policy", "value": "cross-origin"}, {"name": "ETag", "value": "\"b18e85c0f194c93927a8ee8f4ec84434fb4cc6b5\""}, {"name": "Server", "value": "nginx"}, {"name": "Timing-Allow-Origin", "value": "*"}, {"name": "Content-Length", "value": "28680"}, {"name": "Date", "value": "Sun, 17 Oct 2021 18:05:47 GMT"}, {"name": "Connection", "value": "keep-alive"}], "content": {"size": 0, "mimeType": "application/font-woff2", "comment": ""}, "redirectURL": "", "headersSize": 349, "bodySize": 28680, "comment": ""}, "cache": {}, "timings": {"comment": "", "wait": 23, "send": 0, "dns": 0, "ssl": 41, "connect": 64, "blocked": 0, "receive": 1}, "serverIPAddress": "23.59.154.19", "comment": "", "time": 89}, {"pageref": "Duane Hall", "startedDateTime": "2021-10-17T12:05:47.495-06:00", "request": {"method": "GET", "url": "https://p.typekit.net/p.gif?s=2&k=646866_6146688be7110b3c5077b4dc&ht=tk&h=www.voteforhallward6.ca&f=9873.9869.9874.9871.14600.9870.9872&a=646866&js=1.20.0&app=typekit&e=js&_=1634493947327", "httpVersion": "HTTP/1.1", "cookies": [], "headers": [{"name": "Host", "value": "p.typekit.net"}, {"name": "User-Agent", "value": "Mozilla/5.0 (Windows NT 10.0; Win64; x64; rv:93.0) Gecko/20100101 Firefox/93.0"}, {"name": "Accept", "value": "image/avif,image/webp,*/*"}, {"name": "Accept-Language", "value": "en-US,en;q=0.5"}, {"name": "Accept-Encoding", "value": "gzip, deflate, br"}, {"name": "Connection", "value": "keep-alive"}, {"name": "Referer", "value": "https://www.voteforhallward6.ca/"}, {"name": "Sec-Fetch-Dest", "value": "image"}, {"name": "Sec-Fetch-Mode", "value": "no-cors"}, {"name": "Sec-Fetch-Site", "value": "cross-site"}], "queryString": [{"name": "s", "value": "2"}, {"name": "k", "value": "646866_6146688be7110b3c5077b4dc"}, {"name": "ht", "value": "tk"}, {"name": "h", "value": "www.voteforhallward6.ca"}, {"name": "f", "value": "9873.9869.9874.9871.14600.9870.9872"}, {"name": "a", "value": "646866"}, {"name": "js", "value": "1.20.0"}, {"name": "app", "value": "typekit"}, {"name": "e", "value": "js"}, {"name": "_", "value": "1634493947327"}], "headersSize": 545, "bodySize": 0, "comment": ""}, "response": {"status": 200, "statusText": "OK", "httpVersion": "HTTP/1.1", "cookies": [], "headers": [{"name": "Accept-Ranges", "value": "bytes"}, {"name": "Access-Control-Allow-Origin", "value": "*"}, {"name": "Cache-Control", "value": "public, max-age=604800"}, {"name": "Content-Type", "value": "image/gif"}, {"name": "Cross-Origin-Resource-Policy", "value": "cross-origin"}, {"name": "ETag", "value": "\"5f4eee5e-23\""}, {"name": "Last-Modified", "value": "Wed, 02 Sep 2020 00:59:10 GMT"}, {"name": "Server", "value": "nginx"}, {"name": "Content-Length", "value": "35"}, {"name": "Date", "value": "Sun, 17 Oct 2021 18:05:47 GMT"}, {"name": "Connection", "value": "keep-alive"}], "content": {"size": 0, "mimeType": "image/gif", "comment": ""}, "redirectURL": "", "headersSize": 346, "bodySize": 35, "comment": ""}, "cache": {}, "timings": {"comment": "", "wait": 37, "send": 0, "dns": 3, "ssl": 134, "connect": 172, "blocked": 0, "receive": 0}, "serverIPAddress": "23.220.150.220", "comment": "", "time": 214}], "comment": ""}}