{"log": {"version": "1.2", "creator": {"name": "BrowserMob Proxy", "version": "2.1.4", "comment": ""}, "pages": [{"id": "Carter Thomson", "startedDateTime": "2021-10-18T00:07:39.362-06:00", "title": "Carter Thomson", "pageTimings": {"comment": ""}, "comment": ""}], "entries": [{"pageref": "Carter Thomson", "startedDateTime": "2021-10-18T00:07:39.379-06:00", "request": {"method": "GET", "url": "http://carterthomson.com/", "httpVersion": "HTTP/1.1", "cookies": [], "headers": [{"name": "Host", "value": "carterthomson.com"}, {"name": "Proxy-Connection", "value": "keep-alive"}, {"name": "Upgrade-Insecure-Requests", "value": "1"}, {"name": "User-Agent", "value": "Mozilla/5.0 (Windows NT 10.0; Win64; x64) AppleWebKit/537.36 (KHTML, like Gecko) Chrome/94.0.4606.81 Safari/537.36"}, {"name": "Accept", "value": "text/html,application/xhtml+xml,application/xml;q=0.9,image/avif,image/webp,image/apng,*/*;q=0.8,application/signed-exchange;v=b3;q=0.9"}, {"name": "Accept-Encoding", "value": "gzip, deflate"}, {"name": "Accept-Language", "value": "en-US,en;q=0.9"}], "queryString": [], "headersSize": 467, "bodySize": 0, "comment": ""}, "response": {"status": 301, "statusText": "Moved Permanently", "httpVersion": "HTTP/1.1", "cookies": [], "headers": [{"name": "Location", "value": "http://www.carterthomson.com/"}, {"name": "Date", "value": "Mon, 18 Oct 2021 06:07:39 GMT"}, {"name": "Content-Type", "value": "text/html; charset=UTF-8"}, {"name": "Server", "value": "ghs"}, {"name": "Content-Length", "value": "226"}, {"name": "X-XSS-Protection", "value": "0"}, {"name": "X-Frame-Options", "value": "SAMEORIGIN"}], "content": {"size": 0, "mimeType": "text/html; charset=UTF-8", "comment": ""}, "redirectURL": "http://www.carterthomson.com/", "headersSize": 238, "bodySize": 226, "comment": ""}, "cache": {}, "timings": {"comment": "", "receive": 0, "connect": 17, "blocked": 0, "send": 0, "wait": 26, "dns": 0, "ssl": -1}, "serverIPAddress": "216.239.38.21", "comment": "", "time": 45}, {"pageref": "Carter Thomson", "startedDateTime": "2021-10-18T00:07:39.425-06:00", "request": {"method": "GET", "url": "http://www.carterthomson.com/", "httpVersion": "HTTP/1.1", "cookies": [], "headers": [{"name": "Host", "value": "www.carterthomson.com"}, {"name": "Proxy-Connection", "value": "keep-alive"}, {"name": "Upgrade-Insecure-Requests", "value": "1"}, {"name": "User-Agent", "value": "Mozilla/5.0 (Windows NT 10.0; Win64; x64) AppleWebKit/537.36 (KHTML, like Gecko) Chrome/94.0.4606.81 Safari/537.36"}, {"name": "Accept", "value": "text/html,application/xhtml+xml,application/xml;q=0.9,image/avif,image/webp,image/apng,*/*;q=0.8,application/signed-exchange;v=b3;q=0.9"}, {"name": "Accept-Encoding", "value": "gzip, deflate"}, {"name": "Accept-Language", "value": "en-US,en;q=0.9"}], "queryString": [], "headersSize": 475, "bodySize": 0, "comment": ""}, "response": {"status": 301, "statusText": "Moved Permanently", "httpVersion": "HTTP/1.1", "cookies": [], "headers": [{"name": "Content-Type", "value": "application/binary"}, {"name": "Cache-Control", "value": "no-cache, no-store, max-age=0, must-revalidate"}, {"name": "Pragma", "value": "no-cache"}, {"name": "Expires", "value": "Mon, 01 Jan 1990 00:00:00 GMT"}, {"name": "Date", "value": "Mon, 18 Oct 2021 06:07:39 GMT"}, {"name": "Location", "value": "https://www.carterthomson.com/"}, {"name": "Server", "value": "ESF"}, {"name": "Content-Length", "value": "0"}, {"name": "X-XSS-Protection", "value": "0"}, {"name": "X-Frame-Options", "value": "SAMEORIGIN"}, {"name": "X-Content-Type-Options", "value": "nosniff"}], "content": {"size": 0, "mimeType": "application/binary", "comment": ""}, "redirectURL": "https://www.carterthomson.com/", "headersSize": 385, "bodySize": 0, "comment": ""}, "cache": {}, "timings": {"comment": "", "receive": 0, "connect": 18, "blocked": 0, "send": 0, "wait": 69, "dns": 0, "ssl": -1}, "serverIPAddress": "142.250.217.83", "comment": "", "time": 88}, {"pageref": "Carter Thomson", "startedDateTime": "2021-10-18T00:07:41.603-06:00", "request": {"method": "GET", "url": "https://www.carterthomson.com/", "httpVersion": "HTTP/1.1", "cookies": [], "headers": [{"name": "Host", "value": "www.carterthomson.com"}, {"name": "Connection", "value": "keep-alive"}, {"name": "Upgrade-Insecure-Requests", "value": "1"}, {"name": "User-Agent", "value": "Mozilla/5.0 (Windows NT 10.0; Win64; x64) AppleWebKit/537.36 (KHTML, like Gecko) Chrome/94.0.4606.81 Safari/537.36"}, {"name": "Accept", "value": "text/html,application/xhtml+xml,application/xml;q=0.9,image/avif,image/webp,image/apng,*/*;q=0.8,application/signed-exchange;v=b3;q=0.9"}, {"name": "Sec-Fetch-Site", "value": "none"}, {"name": "Sec-Fetch-Mode", "value": "navigate"}, {"name": "Sec-Fetch-User", "value": "?1"}, {"name": "Sec-Fetch-Dest", "value": "document"}, {"name": "sec-ch-ua", "value": "\"Chromium\";v=\"94\", \"Google Chrome\";v=\"94\", \";Not A Brand\";v=\"99\""}, {"name": "sec-ch-ua-mobile", "value": "?0"}, {"name": "sec-ch-ua-platform", "value": "\"Windows\""}, {"name": "Accept-Encoding", "value": "gzip, deflate, br"}, {"name": "Accept-Language", "value": "en-US,en;q=0.9"}], "queryString": [], "headersSize": 669, "bodySize": 0, "comment": ""}, "response": {"status": 200, "statusText": "OK", "httpVersion": "HTTP/1.1", "cookies": [], "headers": [{"name": "Content-Type", "value": "text/html; charset=utf-8"}, {"name": "X-Frame-Options", "value": "DENY"}, {"name": "Cache-Control", "value": "no-cache, no-store, max-age=0, must-revalidate"}, {"name": "Pragma", "value": "no-cache"}, {"name": "Expires", "value": "Mon, 01 Jan 1990 00:00:00 GMT"}, {"name": "Date", "value": "Mon, 18 Oct 2021 06:07:41 GMT"}, {"name": "Content-Security-Policy", "value": "base-uri 'self';object-src 'none';report-uri /_/view/cspreport;script-src 'report-sample' 'nonce-s63ZKus1ySriyM1mImKj+A' 'unsafe-inline' 'unsafe-eval';worker-src 'self';frame-ancestors https://google-admin.corp.google.com/"}, {"name": "Cross-Origin-Opener-Policy-Report-Only", "value": "same-origin; report-to=\"AZM8irbjJqj1AV5BHD51MdaHh7lpD_Vlv2gcHw7IpJALMgk2VS4\""}, {"name": "Report-To", "value": "{\"group\":\"AZM8irbjJqj1AV5BHD51MdaHh7lpD_Vlv2gcHw7IpJALMgk2VS4\",\"max_age\":2592000,\"endpoints\":[{\"url\":\"https://csp.withgoogle.com/csp/report-to/encsid_AZM8irbjJqj1AV5BHD51MdaHh7lpD_Vlv2gcHw7IpJALMgk2VS4\"}]}"}, {"name": "Referrer-Policy", "value": "strict-origin-when-cross-origin"}, {"name": "Server", "value": "ESF"}, {"name": "X-XSS-Protection", "value": "0"}, {"name": "X-Content-Type-Options", "value": "nosniff"}, {"name": "Content-Encoding", "value": "gzip"}, {"name": "Transfer-Encoding", "value": "chunked"}], "content": {"size": 0, "mimeType": "text/html; charset=utf-8", "comment": ""}, "redirectURL": "", "headersSize": 996, "bodySize": 10657, "comment": ""}, "cache": {}, "timings": {"comment": "", "receive": 18, "connect": 2084, "blocked": 0, "send": 0, "wait": 159, "dns": 0, "ssl": 2066}, "serverIPAddress": "142.250.217.83", "comment": "", "time": 2262}, {"pageref": "Carter Thomson", "startedDateTime": "2021-10-18T00:07:41.803-06:00", "request": {"method": "GET", "url": "https://www.gstatic.com/_/atari/_/ss/k=atari.vw.8fDIeR1rJsc.L.W.O/d=1/rs=AGEqA5m_odq35c3EGI8rPx9DBvF-2Pg7cg", "httpVersion": "HTTP/1.1", "cookies": [], "headers": [{"name": "Host", "value": "www.gstatic.com"}, {"name": "Connection", "value": "keep-alive"}, {"name": "sec-ch-ua", "value": "\"Chromium\";v=\"94\", \"Google Chrome\";v=\"94\", \";Not A Brand\";v=\"99\""}, {"name": "sec-ch-ua-mobile", "value": "?0"}, {"name": "User-Agent", "value": "Mozilla/5.0 (Windows NT 10.0; Win64; x64) AppleWebKit/537.36 (KHTML, like Gecko) Chrome/94.0.4606.81 Safari/537.36"}, {"name": "sec-ch-ua-platform", "value": "\"Windows\""}, {"name": "Accept", "value": "text/css,*/*;q=0.1"}, {"name": "Sec-Fetch-Site", "value": "cross-site"}, {"name": "Sec-Fetch-Mode", "value": "no-cors"}, {"name": "Sec-Fetch-Dest", "value": "style"}, {"name": "Referer", "value": "https://www.carterthomson.com/"}, {"name": "Accept-Encoding", "value": "gzip, deflate, br"}, {"name": "Accept-Language", "value": "en-US,en;q=0.9"}], "queryString": [], "headersSize": 622, "bodySize": 0, "comment": ""}, "response": {"status": 200, "statusText": "OK", "httpVersion": "HTTP/1.1", "cookies": [], "headers": [{"name": "Accept-Ranges", "value": "bytes"}, {"name": "Vary", "value": "Accept-Encoding"}, {"name": "Content-Encoding", "value": "gzip"}, {"name": "Content-Type", "value": "text/css; charset=UTF-8"}, {"name": "Access-Control-Allow-Origin", "value": "*"}, {"name": "Cross-Origin-Resource-Policy", "value": "cross-origin"}, {"name": "Cross-Origin-Opener-Policy-Report-Only", "value": "same-origin; report-to=\"apps-sites\""}, {"name": "Report-To", "value": "{\"group\":\"apps-sites\",\"max_age\":2592000,\"endpoints\":[{\"url\":\"https://csp.withgoogle.com/csp/report-to/apps-sites\"}]}"}, {"name": "Content-Length", "value": "85418"}, {"name": "Date", "value": "Tue, 12 Oct 2021 18:44:43 GMT"}, {"name": "Expires", "value": "Wed, 12 Oct 2022 18:44:43 GMT"}, {"name": "Last-Modified", "value": "Tue, 05 Oct 2021 12:34:22 GMT"}, {"name": "X-Content-Type-Options", "value": "nosniff"}, {"name": "Server", "value": "sffe"}, {"name": "X-XSS-Protection", "value": "0"}, {"name": "Age", "value": "472978"}, {"name": "Cache-Control", "value": "public, max-age=31536000"}, {"name": "Alt-Svc", "value": "h3=\":443\"; ma=2592000,h3-29=\":443\"; ma=2592000,h3-T051=\":443\"; ma=2592000,h3-Q050=\":443\"; ma=2592000,h3-Q046=\":443\"; ma=2592000,h3-Q043=\":443\"; ma=2592000,quic=\":443\"; ma=2592000; v=\"46,43\""}], "content": {"size": 0, "mimeType": "text/css; charset=UTF-8", "comment": ""}, "redirectURL": "", "headersSize": 879, "bodySize": 85418, "comment": ""}, "cache": {}, "timings": {"comment": "", "receive": 13, "connect": -1, "blocked": -1, "send": 0, "wait": 18, "dns": -1, "ssl": -1}, "serverIPAddress": "142.250.217.67", "comment": "", "time": 32}, {"pageref": "Carter Thomson", "startedDateTime": "2021-10-18T00:07:41.873-06:00", "request": {"method": "GET", "url": "https://fonts.googleapis.com/css?family=Lato%3A300%2C300italic%2C400%2C400italic%2C700%2C700italic&display=swap", "httpVersion": "HTTP/1.1", "cookies": [], "headers": [{"name": "Host", "value": "fonts.googleapis.com"}, {"name": "Connection", "value": "keep-alive"}, {"name": "sec-ch-ua", "value": "\"Chromium\";v=\"94\", \"Google Chrome\";v=\"94\", \";Not A Brand\";v=\"99\""}, {"name": "sec-ch-ua-mobile", "value": "?0"}, {"name": "User-Agent", "value": "Mozilla/5.0 (Windows NT 10.0; Win64; x64) AppleWebKit/537.36 (KHTML, like Gecko) Chrome/94.0.4606.81 Safari/537.36"}, {"name": "sec-ch-ua-platform", "value": "\"Windows\""}, {"name": "Accept", "value": "text/css,*/*;q=0.1"}, {"name": "Sec-Fetch-Site", "value": "cross-site"}, {"name": "Sec-Fetch-Mode", "value": "no-cors"}, {"name": "Sec-Fetch-Dest", "value": "style"}, {"name": "Referer", "value": "https://www.carterthomson.com/"}, {"name": "Accept-Encoding", "value": "gzip, deflate, br"}, {"name": "Accept-Language", "value": "en-US,en;q=0.9"}], "queryString": [{"name": "family", "value": "Lato:300,300italic,400,400italic,700,700italic"}, {"name": "display", "value": "swap"}], "headersSize": 626, "bodySize": 0, "comment": ""}, "response": {"status": 200, "statusText": "OK", "httpVersion": "HTTP/1.1", "cookies": [], "headers": [{"name": "Content-Type", "value": "text/css; charset=utf-8"}, {"name": "Access-Control-Allow-Origin", "value": "*"}, {"name": "Timing-Allow-Origin", "value": "*"}, {"name": "Link", "value": "<https://fonts.gstatic.com>; rel=preconnect; crossorigin"}, {"name": "Strict-Transport-Security", "value": "max-age=31536000"}, {"name": "Expires", "value": "Mon, 18 Oct 2021 06:07:41 GMT"}, {"name": "Date", "value": "Mon, 18 Oct 2021 06:07:41 GMT"}, {"name": "Cache-Control", "value": "private, max-age=86400, stale-while-revalidate=604800"}, {"name": "Last-Modified", "value": "Mon, 18 Oct 2021 05:19:17 GMT"}, {"name": "Cross-Origin-Resource-Policy", "value": "cross-origin"}, {"name": "Cross-Origin-Opener-Policy-Report-Only", "value": "same-origin; report-to=\"AZM8iraMxxUfRnRum-EGst9UuHcPNVSf9Kp1_90wIgU\""}, {"name": "Report-To", "value": "{\"group\":\"AZM8iraMxxUfRnRum-EGst9UuHcPNVSf9Kp1_90wIgU\",\"max_age\":2592000,\"endpoints\":[{\"url\":\"https://csp.withgoogle.com/csp/report-to/encsid_AZM8iraMxxUfRnRum-EGst9UuHcPNVSf9Kp1_90wIgU\"}]}"}, {"name": "Content-Encoding", "value": "gzip"}, {"name": "Server", "value": "ESF"}, {"name": "X-XSS-Protection", "value": "0"}, {"name": "X-Frame-Options", "value": "SAMEORIGIN"}, {"name": "X-Content-Type-Options", "value": "nosniff"}, {"name": "Alt-Svc", "value": "h3=\":443\"; ma=2592000,h3-29=\":443\"; ma=2592000,h3-T051=\":443\"; ma=2592000,h3-Q050=\":443\"; ma=2592000,h3-Q046=\":443\"; ma=2592000,h3-Q043=\":443\"; ma=2592000,quic=\":443\"; ma=2592000; v=\"46,43\""}, {"name": "Transfer-Encoding", "value": "chunked"}], "content": {"size": 0, "mimeType": "text/css; charset=utf-8", "comment": ""}, "redirectURL": "", "headersSize": 1122, "bodySize": 485, "comment": ""}, "cache": {}, "timings": {"comment": "", "receive": 0, "connect": 70, "blocked": 0, "send": 0, "wait": 26, "dns": 0, "ssl": 51}, "serverIPAddress": "142.250.69.202", "comment": "", "time": 98}, {"pageref": "Carter Thomson", "startedDateTime": "2021-10-18T00:07:41.874-06:00", "request": {"method": "GET", "url": "https://fonts.googleapis.com/css?family=Google+Sans:400,500|Roboto:300,400,500,700|Source+Code+Pro:400,700&display=swap", "httpVersion": "HTTP/1.1", "cookies": [], "headers": [{"name": "Host", "value": "fonts.googleapis.com"}, {"name": "Connection", "value": "keep-alive"}, {"name": "sec-ch-ua", "value": "\"Chromium\";v=\"94\", \"Google Chrome\";v=\"94\", \";Not A Brand\";v=\"99\""}, {"name": "sec-ch-ua-mobile", "value": "?0"}, {"name": "User-Agent", "value": "Mozilla/5.0 (Windows NT 10.0; Win64; x64) AppleWebKit/537.36 (KHTML, like Gecko) Chrome/94.0.4606.81 Safari/537.36"}, {"name": "sec-ch-ua-platform", "value": "\"Windows\""}, {"name": "Accept", "value": "text/css,*/*;q=0.1"}, {"name": "Sec-Fetch-Site", "value": "cross-site"}, {"name": "Sec-Fetch-Mode", "value": "no-cors"}, {"name": "Sec-Fetch-Dest", "value": "style"}, {"name": "Referer", "value": "https://www.carterthomson.com/"}, {"name": "Accept-Encoding", "value": "gzip, deflate, br"}, {"name": "Accept-Language", "value": "en-US,en;q=0.9"}], "queryString": [{"name": "family", "value": "Google Sans:400,500|Roboto:300,400,500,700|Source Code Pro:400,700"}, {"name": "display", "value": "swap"}], "headersSize": 634, "bodySize": 0, "comment": ""}, "response": {"status": 200, "statusText": "OK", "httpVersion": "HTTP/1.1", "cookies": [], "headers": [{"name": "Content-Type", "value": "text/css; charset=utf-8"}, {"name": "Access-Control-Allow-Origin", "value": "*"}, {"name": "Timing-Allow-Origin", "value": "*"}, {"name": "Link", "value": "<https://fonts.gstatic.com>; rel=preconnect; crossorigin"}, {"name": "Strict-Transport-Security", "value": "max-age=31536000"}, {"name": "Expires", "value": "Mon, 18 Oct 2021 06:07:41 GMT"}, {"name": "Date", "value": "Mon, 18 Oct 2021 06:07:41 GMT"}, {"name": "Cache-Control", "value": "private, max-age=86400, stale-while-revalidate=604800"}, {"name": "Last-Modified", "value": "Mon, 18 Oct 2021 05:42:38 GMT"}, {"name": "Report-To", "value": "{\"group\":\"AZM8iraMxxUfRnRum-EGst9UuHcPNVSf9Kp1_90wIgU\",\"max_age\":2592000,\"endpoints\":[{\"url\":\"https://csp.withgoogle.com/csp/report-to/encsid_AZM8iraMxxUfRnRum-EGst9UuHcPNVSf9Kp1_90wIgU\"}]}"}, {"name": "Cross-Origin-Opener-Policy-Report-Only", "value": "same-origin; report-to=\"AZM8iraMxxUfRnRum-EGst9UuHcPNVSf9Kp1_90wIgU\""}, {"name": "Cross-Origin-Resource-Policy", "value": "cross-origin"}, {"name": "Content-Encoding", "value": "gzip"}, {"name": "Server", "value": "ESF"}, {"name": "X-XSS-Protection", "value": "0"}, {"name": "X-Frame-Options", "value": "SAMEORIGIN"}, {"name": "X-Content-Type-Options", "value": "nosniff"}, {"name": "Alt-Svc", "value": "h3=\":443\"; ma=2592000,h3-29=\":443\"; ma=2592000,h3-T051=\":443\"; ma=2592000,h3-Q050=\":443\"; ma=2592000,h3-Q046=\":443\"; ma=2592000,h3-Q043=\":443\"; ma=2592000,quic=\":443\"; ma=2592000; v=\"46,43\""}, {"name": "Transfer-Encoding", "value": "chunked"}], "content": {"size": 0, "mimeType": "text/css; charset=utf-8", "comment": ""}, "redirectURL": "", "headersSize": 1122, "bodySize": 1066, "comment": ""}, "cache": {}, "timings": {"comment": "", "receive": 0, "connect": 70, "blocked": 0, "send": 0, "wait": 27, "dns": 0, "ssl": 51}, "serverIPAddress": "142.250.69.202", "comment": "", "time": 99}, {"pageref": "Carter Thomson", "startedDateTime": "2021-10-18T00:07:41.891-06:00", "request": {"method": "GET", "url": "https://apis.google.com/js/client.js?onload=gapiLoaded", "httpVersion": "HTTP/1.1", "cookies": [], "headers": [{"name": "Host", "value": "apis.google.com"}, {"name": "Connection", "value": "keep-alive"}, {"name": "sec-ch-ua", "value": "\"Chromium\";v=\"94\", \"Google Chrome\";v=\"94\", \";Not A Brand\";v=\"99\""}, {"name": "sec-ch-ua-mobile", "value": "?0"}, {"name": "User-Agent", "value": "Mozilla/5.0 (Windows NT 10.0; Win64; x64) AppleWebKit/537.36 (KHTML, like Gecko) Chrome/94.0.4606.81 Safari/537.36"}, {"name": "sec-ch-ua-platform", "value": "\"Windows\""}, {"name": "Accept", "value": "*/*"}, {"name": "Sec-Fetch-Site", "value": "cross-site"}, {"name": "Sec-Fetch-Mode", "value": "no-cors"}, {"name": "Sec-Fetch-Dest", "value": "script"}, {"name": "Referer", "value": "https://www.carterthomson.com/"}, {"name": "Accept-Encoding", "value": "gzip, deflate, br"}, {"name": "Accept-Language", "value": "en-US,en;q=0.9"}, {"name": "Cookie", "value": "1P_JAR=2021-10-18-06; NID=511=dT7Gac5gV3hPshpRqaBJeNScx2hY34UV1i6I1Qxo6lTBFHvAF-TB8h5-ShSxU-q2en9sN6GW5KhQq63GHhazKAKTarHRCeKWkfjx-vdKmFSKDyzyICHnG-54L4NLjX4UR4Lr8rUczWcwcu4pOlwbAmREDvV4RT6_GaXEBM6VXuw"}], "queryString": [{"name": "onload", "value": "gapiLoaded"}], "headersSize": 766, "bodySize": 0, "comment": ""}, "response": {"status": 200, "statusText": "OK", "httpVersion": "HTTP/1.1", "cookies": [], "headers": [{"name": "Content-Type", "value": "application/javascript; charset=utf-8"}, {"name": "x-ua-compatible", "value": "IE=edge, chrome=1"}, {"name": "Timing-Allow-Origin", "value": "*"}, {"name": "ETag", "value": "\"df85deb5ab1be473efa82737997c783f\""}, {"name": "Access-Control-Allow-Origin", "value": "*"}, {"name": "Expires", "value": "Mon, 18 Oct 2021 06:07:41 GMT"}, {"name": "Date", "value": "Mon, 18 Oct 2021 06:07:41 GMT"}, {"name": "Cache-Control", "value": "private, max-age=1800, stale-while-revalidate=1800"}, {"name": "Report-To", "value": "{\"group\":\"AZM8iraZH88pL4jQdjcWpuaSZEaZk6SzMEy_nItKJ7e9QFtt\",\"max_age\":2592000,\"endpoints\":[{\"url\":\"https://csp.withgoogle.com/csp/report-to/encsid_AZM8iraZH88pL4jQdjcWpuaSZEaZk6SzMEy_nItKJ7e9QFtt\"}]}"}, {"name": "Content-Security-Policy", "value": "script-src 'report-sample' 'nonce-OD1yZpuYZrRLy/gEDuiuXA' 'unsafe-inline' 'strict-dynamic' https: http: 'unsafe-eval';object-src 'none';base-uri 'self';report-uri /_/cspreport"}, {"name": "Cross-Origin-Resource-Policy", "value": "cross-origin"}, {"name": "Cross-Origin-Opener-Policy-Report-Only", "value": "same-origin; report-to=\"AZM8iraZH88pL4jQdjcWpuaSZEaZk6SzMEy_nItKJ7e9QFtt\""}, {"name": "Strict-Transport-Security", "value": "max-age=31536000"}, {"name": "Content-Encoding", "value": "gzip"}, {"name": "Server", "value": "ESF"}, {"name": "X-XSS-Protection", "value": "0"}, {"name": "X-Frame-Options", "value": "SAMEORIGIN"}, {"name": "X-Content-Type-Options", "value": "nosniff"}, {"name": "Alt-Svc", "value": "h3=\":443\"; ma=2592000,h3-29=\":443\"; ma=2592000,h3-T051=\":443\"; ma=2592000,h3-Q050=\":443\"; ma=2592000,h3-Q046=\":443\"; ma=2592000,h3-Q043=\":443\"; ma=2592000,quic=\":443\"; ma=2592000; v=\"46,43\""}, {"name": "Transfer-Encoding", "value": "chunked"}], "content": {"size": 0, "mimeType": "application/javascript; charset=utf-8", "comment": ""}, "redirectURL": "", "headersSize": 1318, "bodySize": 4979, "comment": ""}, "cache": {}, "timings": {"comment": "", "receive": 1, "connect": 82, "blocked": 0, "send": 0, "wait": 56, "dns": 4, "ssl": 54}, "serverIPAddress": "142.250.217.110", "comment": "", "time": 145}, {"pageref": "Carter Thomson", "startedDateTime": "2021-10-18T00:07:41.906-06:00", "request": {"method": "GET", "url": "https://www.gstatic.com/_/atari/_/js/k=atari.vw.en_US.-uc1e11mbic.O/d=1/rs=AGEqA5mq1x26X6hQffmM02K3S-EwBTeLiA/m=view", "httpVersion": "HTTP/1.1", "cookies": [], "headers": [{"name": "Host", "value": "www.gstatic.com"}, {"name": "Connection", "value": "keep-alive"}, {"name": "sec-ch-ua", "value": "\"Chromium\";v=\"94\", \"Google Chrome\";v=\"94\", \";Not A Brand\";v=\"99\""}, {"name": "sec-ch-ua-mobile", "value": "?0"}, {"name": "User-Agent", "value": "Mozilla/5.0 (Windows NT 10.0; Win64; x64) AppleWebKit/537.36 (KHTML, like Gecko) Chrome/94.0.4606.81 Safari/537.36"}, {"name": "sec-ch-ua-platform", "value": "\"Windows\""}, {"name": "Accept", "value": "*/*"}, {"name": "Sec-Fetch-Site", "value": "cross-site"}, {"name": "Sec-Fetch-Mode", "value": "no-cors"}, {"name": "Sec-Fetch-Dest", "value": "script"}, {"name": "Referer", "value": "https://www.carterthomson.com/"}, {"name": "Accept-Encoding", "value": "gzip, deflate, br"}, {"name": "Accept-Language", "value": "en-US,en;q=0.9"}], "queryString": [], "headersSize": 617, "bodySize": 0, "comment": ""}, "response": {"status": 200, "statusText": "OK", "httpVersion": "HTTP/1.1", "cookies": [], "headers": [{"name": "Accept-Ranges", "value": "bytes"}, {"name": "Vary", "value": "Accept-Encoding"}, {"name": "Content-Encoding", "value": "gzip"}, {"name": "Content-Type", "value": "text/javascript; charset=UTF-8"}, {"name": "Access-Control-Allow-Origin", "value": "*"}, {"name": "Cross-Origin-Resource-Policy", "value": "cross-origin"}, {"name": "Cross-Origin-Opener-Policy-Report-Only", "value": "same-origin; report-to=\"apps-sites\""}, {"name": "Report-To", "value": "{\"group\":\"apps-sites\",\"max_age\":2592000,\"endpoints\":[{\"url\":\"https://csp.withgoogle.com/csp/report-to/apps-sites\"}]}"}, {"name": "Content-Length", "value": "160680"}, {"name": "Date", "value": "Mon, 11 Oct 2021 14:30:30 GMT"}, {"name": "Expires", "value": "Tue, 11 Oct 2022 14:30:30 GMT"}, {"name": "Last-Modified", "value": "Tue, 05 Oct 2021 12:34:22 GMT"}, {"name": "X-Content-Type-Options", "value": "nosniff"}, {"name": "Server", "value": "sffe"}, {"name": "X-XSS-Protection", "value": "0"}, {"name": "Cache-Control", "value": "public, max-age=31536000"}, {"name": "Age", "value": "574631"}, {"name": "Alt-Svc", "value": "h3=\":443\"; ma=2592000,h3-29=\":443\"; ma=2592000,h3-T051=\":443\"; ma=2592000,h3-Q050=\":443\"; ma=2592000,h3-Q046=\":443\"; ma=2592000,h3-Q043=\":443\"; ma=2592000,quic=\":443\"; ma=2592000; v=\"46,43\""}], "content": {"size": 0, "mimeType": "text/javascript; charset=UTF-8", "comment": ""}, "redirectURL": "", "headersSize": 887, "bodySize": 160680, "comment": ""}, "cache": {}, "timings": {"comment": "", "receive": 23, "connect": -1, "blocked": -1, "send": 0, "wait": 18, "dns": -1, "ssl": -1}, "serverIPAddress": "142.250.217.67", "comment": "", "time": 42}, {"pageref": "Carter Thomson", "startedDateTime": "2021-10-18T00:07:42.028-06:00", "request": {"method": "GET", "url": "https://apis.google.com/_/scs/apps-static/_/js/k=oz.gapi.en_US.2lM46t9-YIo.O/m=client/rt=j/sv=1/d=1/ed=1/am=AQ/rs=AGLTcCOhwmvF7Fsri7fVyVVvLH1eaFC1jg/cb=gapi.loaded_0", "httpVersion": "HTTP/1.1", "cookies": [], "headers": [{"name": "Host", "value": "apis.google.com"}, {"name": "Connection", "value": "keep-alive"}, {"name": "sec-ch-ua", "value": "\"Chromium\";v=\"94\", \"Google Chrome\";v=\"94\", \";Not A Brand\";v=\"99\""}, {"name": "sec-ch-ua-mobile", "value": "?0"}, {"name": "User-Agent", "value": "Mozilla/5.0 (Windows NT 10.0; Win64; x64) AppleWebKit/537.36 (KHTML, like Gecko) Chrome/94.0.4606.81 Safari/537.36"}, {"name": "sec-ch-ua-platform", "value": "\"Windows\""}, {"name": "Accept", "value": "*/*"}, {"name": "Sec-Fetch-Site", "value": "cross-site"}, {"name": "Sec-Fetch-Mode", "value": "no-cors"}, {"name": "Sec-Fetch-Dest", "value": "script"}, {"name": "Referer", "value": "https://www.carterthomson.com/"}, {"name": "Accept-Encoding", "value": "gzip, deflate, br"}, {"name": "Accept-Language", "value": "en-US,en;q=0.9"}, {"name": "Cookie", "value": "1P_JAR=2021-10-18-06; NID=511=dT7Gac5gV3hPshpRqaBJeNScx2hY34UV1i6I1Qxo6lTBFHvAF-TB8h5-ShSxU-q2en9sN6GW5KhQq63GHhazKAKTarHRCeKWkfjx-vdKmFSKDyzyICHnG-54L4NLjX4UR4Lr8rUczWcwcu4pOlwbAmREDvV4RT6_GaXEBM6VXuw"}], "queryString": [], "headersSize": 877, "bodySize": 0, "comment": ""}, "response": {"status": 200, "statusText": "OK", "httpVersion": "HTTP/1.1", "cookies": [], "headers": [{"name": "Accept-Ranges", "value": "bytes"}, {"name": "Vary", "value": "Accept-Encoding, Origin"}, {"name": "Content-Encoding", "value": "gzip"}, {"name": "Content-Type", "value": "text/javascript; charset=UTF-8"}, {"name": "Content-Security-Policy-Report-Only", "value": "require-trusted-types-for 'script'; report-uri https://csp.withgoogle.com/csp/social-frontend-mpm-access"}, {"name": "Cross-Origin-Resource-Policy", "value": "cross-origin"}, {"name": "Cross-Origin-Opener-Policy-Report-Only", "value": "same-origin; report-to=\"social-frontend-mpm-access\""}, {"name": "Report-To", "value": "{\"group\":\"social-frontend-mpm-access\",\"max_age\":2592000,\"endpoints\":[{\"url\":\"https://csp.withgoogle.com/csp/report-to/social-frontend-mpm-access\"}]}"}, {"name": "Content-Length", "value": "107877"}, {"name": "Date", "value": "Tue, 12 Oct 2021 10:46:32 GMT"}, {"name": "Expires", "value": "Wed, 12 Oct 2022 10:46:32 GMT"}, {"name": "Last-Modified", "value": "Fri, 10 Sep 2021 23:24:10 GMT"}, {"name": "X-Content-Type-Options", "value": "nosniff"}, {"name": "Server", "value": "sffe"}, {"name": "X-XSS-Protection", "value": "0"}, {"name": "Cache-Control", "value": "public, immutable, max-age=31536000"}, {"name": "Age", "value": "501669"}, {"name": "Alt-Svc", "value": "h3=\":443\"; ma=2592000,h3-29=\":443\"; ma=2592000,h3-T051=\":443\"; ma=2592000,h3-Q050=\":443\"; ma=2592000,h3-Q046=\":443\"; ma=2592000,h3-Q043=\":443\"; ma=2592000,quic=\":443\"; ma=2592000; v=\"46,43\""}], "content": {"size": 0, "mimeType": "text/javascript; charset=UTF-8", "comment": ""}, "redirectURL": "", "headersSize": 1065, "bodySize": 107877, "comment": ""}, "cache": {}, "timings": {"comment": "", "receive": 73, "connect": 68, "blocked": 0, "send": 0, "wait": 19, "dns": 0, "ssl": 51}, "serverIPAddress": "142.250.217.110", "comment": "", "time": 161}, {"pageref": "Carter Thomson", "startedDateTime": "2021-10-18T00:07:42.042-06:00", "request": {"method": "GET", "url": "https://www.gstatic.com/_/atari/_/js/k=atari.vw.en_US.-uc1e11mbic.O/d=0/rs=AGEqA5mq1x26X6hQffmM02K3S-EwBTeLiA/m=sy11,sy12,sy10,FoQBg", "httpVersion": "HTTP/1.1", "cookies": [], "headers": [{"name": "Host", "value": "www.gstatic.com"}, {"name": "Connection", "value": "keep-alive"}, {"name": "sec-ch-ua", "value": "\"Chromium\";v=\"94\", \"Google Chrome\";v=\"94\", \";Not A Brand\";v=\"99\""}, {"name": "sec-ch-ua-mobile", "value": "?0"}, {"name": "User-Agent", "value": "Mozilla/5.0 (Windows NT 10.0; Win64; x64) AppleWebKit/537.36 (KHTML, like Gecko) Chrome/94.0.4606.81 Safari/537.36"}, {"name": "sec-ch-ua-platform", "value": "\"Windows\""}, {"name": "Accept", "value": "*/*"}, {"name": "Sec-Fetch-Site", "value": "cross-site"}, {"name": "Sec-Fetch-Mode", "value": "no-cors"}, {"name": "Sec-Fetch-Dest", "value": "script"}, {"name": "Referer", "value": "https://www.carterthomson.com/"}, {"name": "Accept-Encoding", "value": "gzip, deflate, br"}, {"name": "Accept-Language", "value": "en-US,en;q=0.9"}], "queryString": [], "headersSize": 633, "bodySize": 0, "comment": ""}, "response": {"status": 200, "statusText": "OK", "httpVersion": "HTTP/1.1", "cookies": [], "headers": [{"name": "Accept-Ranges", "value": "bytes"}, {"name": "Vary", "value": "Accept-Encoding"}, {"name": "Content-Encoding", "value": "gzip"}, {"name": "Content-Type", "value": "text/javascript; charset=UTF-8"}, {"name": "Access-Control-Allow-Origin", "value": "*"}, {"name": "Cross-Origin-Resource-Policy", "value": "cross-origin"}, {"name": "Cross-Origin-Opener-Policy-Report-Only", "value": "same-origin; report-to=\"apps-sites\""}, {"name": "Report-To", "value": "{\"group\":\"apps-sites\",\"max_age\":2592000,\"endpoints\":[{\"url\":\"https://csp.withgoogle.com/csp/report-to/apps-sites\"}]}"}, {"name": "Content-Length", "value": "11996"}, {"name": "Date", "value": "Mon, 11 Oct 2021 14:30:30 GMT"}, {"name": "Expires", "value": "Tue, 11 Oct 2022 14:30:30 GMT"}, {"name": "Last-Modified", "value": "Tue, 05 Oct 2021 12:34:22 GMT"}, {"name": "X-Content-Type-Options", "value": "nosniff"}, {"name": "Server", "value": "sffe"}, {"name": "X-XSS-Protection", "value": "0"}, {"name": "Cache-Control", "value": "public, max-age=31536000"}, {"name": "Age", "value": "574631"}, {"name": "Alt-Svc", "value": "h3=\":443\"; ma=2592000,h3-29=\":443\"; ma=2592000,h3-T051=\":443\"; ma=2592000,h3-Q050=\":443\"; ma=2592000,h3-Q046=\":443\"; ma=2592000,h3-Q043=\":443\"; ma=2592000,quic=\":443\"; ma=2592000; v=\"46,43\""}], "content": {"size": 0, "mimeType": "text/javascript; charset=UTF-8", "comment": ""}, "redirectURL": "", "headersSize": 886, "bodySize": 11996, "comment": ""}, "cache": {}, "timings": {"comment": "", "receive": 1, "connect": -1, "blocked": -1, "send": 0, "wait": 33, "dns": -1, "ssl": -1}, "serverIPAddress": "142.250.217.67", "comment": "", "time": 35}, {"pageref": "Carter Thomson", "startedDateTime": "2021-10-18T00:07:42.047-06:00", "request": {"method": "GET", "url": "https://fonts.gstatic.com/s/roboto/v29/KFOmCnqEu92Fr1Mu4mxK.woff2", "httpVersion": "HTTP/1.1", "cookies": [], "headers": [{"name": "Host", "value": "fonts.gstatic.com"}, {"name": "Connection", "value": "keep-alive"}, {"name": "sec-ch-ua", "value": "\"Chromium\";v=\"94\", \"Google Chrome\";v=\"94\", \";Not A Brand\";v=\"99\""}, {"name": "Origin", "value": "https://www.carterthomson.com"}, {"name": "sec-ch-ua-mobile", "value": "?0"}, {"name": "User-Agent", "value": "Mozilla/5.0 (Windows NT 10.0; Win64; x64) AppleWebKit/537.36 (KHTML, like Gecko) Chrome/94.0.4606.81 Safari/537.36"}, {"name": "sec-ch-ua-platform", "value": "\"Windows\""}, {"name": "Accept", "value": "*/*"}, {"name": "Sec-Fetch-Site", "value": "cross-site"}, {"name": "Sec-Fetch-Mode", "value": "cors"}, {"name": "Sec-Fetch-Dest", "value": "font"}, {"name": "Referer", "value": "https://fonts.googleapis.com/"}, {"name": "Accept-Encoding", "value": "gzip, deflate, br"}, {"name": "Accept-Language", "value": "en-US,en;q=0.9"}], "queryString": [], "headersSize": 599, "bodySize": 0, "comment": ""}, "response": {"status": 200, "statusText": "OK", "httpVersion": "HTTP/1.1", "cookies": [], "headers": [{"name": "Accept-Ranges", "value": "bytes"}, {"name": "Content-Type", "value": "font/woff2"}, {"name": "Access-Control-Allow-Origin", "value": "*"}, {"name": "Content-Security-Policy-Report-Only", "value": "require-trusted-types-for 'script'; report-uri https://csp.withgoogle.com/csp/apps-themes"}, {"name": "Cross-Origin-Resource-Policy", "value": "cross-origin"}, {"name": "Cross-Origin-Opener-Policy-Report-Only", "value": "same-origin; report-to=\"apps-themes\""}, {"name": "Report-To", "value": "{\"group\":\"apps-themes\",\"max_age\":2592000,\"endpoints\":[{\"url\":\"https://csp.withgoogle.com/csp/report-to/apps-themes\"}]}"}, {"name": "Timing-Allow-Origin", "value": "*"}, {"name": "Content-Length", "value": "15688"}, {"name": "Date", "value": "Wed, 13 Oct 2021 06:39:53 GMT"}, {"name": "Expires", "value": "Thu, 13 Oct 2022 06:39:53 GMT"}, {"name": "Last-Modified", "value": "Wed, 22 Sep 2021 16:13:19 GMT"}, {"name": "X-Content-Type-Options", "value": "nosniff"}, {"name": "Server", "value": "sffe"}, {"name": "X-XSS-Protection", "value": "0"}, {"name": "Age", "value": "430068"}, {"name": "Cache-Control", "value": "public, max-age=31536000"}, {"name": "Alt-Svc", "value": "h3=\":443\"; ma=2592000,h3-29=\":443\"; ma=2592000,h3-T051=\":443\"; ma=2592000,h3-Q050=\":443\"; ma=2592000,h3-Q046=\":443\"; ma=2592000,h3-Q043=\":443\"; ma=2592000,quic=\":443\"; ma=2592000; v=\"46,43\""}], "content": {"size": 0, "mimeType": "font/woff2", "comment": ""}, "redirectURL": "", "headersSize": 974, "bodySize": 15688, "comment": ""}, "cache": {}, "timings": {"comment": "", "receive": 18, "connect": 75, "blocked": 0, "send": 0, "wait": 28, "dns": 0, "ssl": 57}, "serverIPAddress": "142.251.33.99", "comment": "", "time": 123}, {"pageref": "Carter Thomson", "startedDateTime": "2021-10-18T00:07:42.053-06:00", "request": {"method": "GET", "url": "https://www.gstatic.com/_/atari/_/js/k=atari.vw.en_US.-uc1e11mbic.O/d=0/rs=AGEqA5mq1x26X6hQffmM02K3S-EwBTeLiA/m=MpJwZc,n73qwf,A4UTCb,qAKInc,syu,TGYpv,syo,YXyON,sy2d,abQiW,qEW1W,KUM7Z,oNFsLb,sy3c,sy3d,sy3e,xQtZb,yf2Bs,sy2,sy7,yyxWAc,sy2g,SM1lmd,sy6,sym,syn,sy5,syl,RRzQxe,syp,YV8yqd,sy8,sya,sy2e,syb,sy9,fNFZH,sy2f,sy14,sy1d,syc,RrXLpc,cgRV2c,sy1e,o1L5Wb,X4BaPc,syw,Md9ENb", "httpVersion": "HTTP/1.1", "cookies": [], "headers": [{"name": "Host", "value": "www.gstatic.com"}, {"name": "Connection", "value": "keep-alive"}, {"name": "sec-ch-ua", "value": "\"Chromium\";v=\"94\", \"Google Chrome\";v=\"94\", \";Not A Brand\";v=\"99\""}, {"name": "sec-ch-ua-mobile", "value": "?0"}, {"name": "User-Agent", "value": "Mozilla/5.0 (Windows NT 10.0; Win64; x64) AppleWebKit/537.36 (KHTML, like Gecko) Chrome/94.0.4606.81 Safari/537.36"}, {"name": "sec-ch-ua-platform", "value": "\"Windows\""}, {"name": "Accept", "value": "*/*"}, {"name": "Sec-Fetch-Site", "value": "cross-site"}, {"name": "Sec-Fetch-Mode", "value": "no-cors"}, {"name": "Sec-Fetch-Dest", "value": "script"}, {"name": "Referer", "value": "https://www.carterthomson.com/"}, {"name": "Accept-Encoding", "value": "gzip, deflate, br"}, {"name": "Accept-Language", "value": "en-US,en;q=0.9"}], "queryString": [], "headersSize": 872, "bodySize": 0, "comment": ""}, "response": {"status": 200, "statusText": "OK", "httpVersion": "HTTP/1.1", "cookies": [], "headers": [{"name": "Accept-Ranges", "value": "bytes"}, {"name": "Vary", "value": "Accept-Encoding"}, {"name": "Content-Encoding", "value": "gzip"}, {"name": "Content-Type", "value": "text/javascript; charset=UTF-8"}, {"name": "Access-Control-Allow-Origin", "value": "*"}, {"name": "Cross-Origin-Resource-Policy", "value": "cross-origin"}, {"name": "Cross-Origin-Opener-Policy-Report-Only", "value": "same-origin; report-to=\"apps-sites\""}, {"name": "Report-To", "value": "{\"group\":\"apps-sites\",\"max_age\":2592000,\"endpoints\":[{\"url\":\"https://csp.withgoogle.com/csp/report-to/apps-sites\"}]}"}, {"name": "Content-Length", "value": "24127"}, {"name": "Date", "value": "Mon, 11 Oct 2021 14:31:09 GMT"}, {"name": "Expires", "value": "Tue, 11 Oct 2022 14:31:09 GMT"}, {"name": "Last-Modified", "value": "Tue, 05 Oct 2021 12:34:22 GMT"}, {"name": "X-Content-Type-Options", "value": "nosniff"}, {"name": "Server", "value": "sffe"}, {"name": "X-XSS-Protection", "value": "0"}, {"name": "Cache-Control", "value": "public, max-age=31536000"}, {"name": "Age", "value": "574592"}, {"name": "Alt-Svc", "value": "h3=\":443\"; ma=2592000,h3-29=\":443\"; ma=2592000,h3-T051=\":443\"; ma=2592000,h3-Q050=\":443\"; ma=2592000,h3-Q046=\":443\"; ma=2592000,h3-Q043=\":443\"; ma=2592000,quic=\":443\"; ma=2592000; v=\"46,43\""}], "content": {"size": 0, "mimeType": "text/javascript; charset=UTF-8", "comment": ""}, "redirectURL": "", "headersSize": 886, "bodySize": 24127, "comment": ""}, "cache": {}, "timings": {"comment": "", "receive": 2, "connect": -1, "blocked": -1, "send": 0, "wait": 28, "dns": -1, "ssl": -1}, "serverIPAddress": "142.250.217.67", "comment": "", "time": 31}, {"pageref": "Carter Thomson", "startedDateTime": "2021-10-18T00:07:42.080-06:00", "request": {"method": "GET", "url": "https://www.gstatic.com/_/atari/_/js/k=atari.vw.en_US.-uc1e11mbic.O/d=0/rs=AGEqA5mq1x26X6hQffmM02K3S-EwBTeLiA/m=sy34,IZT63,vfuNJf,sy2x,sy31,sy35,sy3f,sy3g,siKnQd,sy2v,sy33,sy37,YNjGDd,sy36,sy38,PrPYRd,hc6Ubd,sy3h,SpsfSb,sy1z,sy2c,sy2y,sy30,zbML3c", "httpVersion": "HTTP/1.1", "cookies": [], "headers": [{"name": "Host", "value": "www.gstatic.com"}, {"name": "Connection", "value": "keep-alive"}, {"name": "sec-ch-ua", "value": "\"Chromium\";v=\"94\", \"Google Chrome\";v=\"94\", \";Not A Brand\";v=\"99\""}, {"name": "sec-ch-ua-mobile", "value": "?0"}, {"name": "User-Agent", "value": "Mozilla/5.0 (Windows NT 10.0; Win64; x64) AppleWebKit/537.36 (KHTML, like Gecko) Chrome/94.0.4606.81 Safari/537.36"}, {"name": "sec-ch-ua-platform", "value": "\"Windows\""}, {"name": "Accept", "value": "*/*"}, {"name": "Sec-Fetch-Site", "value": "cross-site"}, {"name": "Sec-Fetch-Mode", "value": "no-cors"}, {"name": "Sec-Fetch-Dest", "value": "script"}, {"name": "Referer", "value": "https://www.carterthomson.com/"}, {"name": "Accept-Encoding", "value": "gzip, deflate, br"}, {"name": "Accept-Language", "value": "en-US,en;q=0.9"}], "queryString": [], "headersSize": 747, "bodySize": 0, "comment": ""}, "response": {"status": 200, "statusText": "OK", "httpVersion": "HTTP/1.1", "cookies": [], "headers": [{"name": "Accept-Ranges", "value": "bytes"}, {"name": "Vary", "value": "Accept-Encoding"}, {"name": "Content-Encoding", "value": "gzip"}, {"name": "Content-Type", "value": "text/javascript; charset=UTF-8"}, {"name": "Access-Control-Allow-Origin", "value": "*"}, {"name": "Cross-Origin-Resource-Policy", "value": "cross-origin"}, {"name": "Cross-Origin-Opener-Policy-Report-Only", "value": "same-origin; report-to=\"apps-sites\""}, {"name": "Report-To", "value": "{\"group\":\"apps-sites\",\"max_age\":2592000,\"endpoints\":[{\"url\":\"https://csp.withgoogle.com/csp/report-to/apps-sites\"}]}"}, {"name": "Content-Length", "value": "9621"}, {"name": "Date", "value": "Mon, 11 Oct 2021 14:30:30 GMT"}, {"name": "Expires", "value": "Tue, 11 Oct 2022 14:30:30 GMT"}, {"name": "Last-Modified", "value": "Tue, 05 Oct 2021 12:34:22 GMT"}, {"name": "X-Content-Type-Options", "value": "nosniff"}, {"name": "Server", "value": "sffe"}, {"name": "X-XSS-Protection", "value": "0"}, {"name": "Cache-Control", "value": "public, max-age=31536000"}, {"name": "Age", "value": "574631"}, {"name": "Alt-Svc", "value": "h3=\":443\"; ma=2592000,h3-29=\":443\"; ma=2592000,h3-T051=\":443\"; ma=2592000,h3-Q050=\":443\"; ma=2592000,h3-Q046=\":443\"; ma=2592000,h3-Q043=\":443\"; ma=2592000,quic=\":443\"; ma=2592000; v=\"46,43\""}], "content": {"size": 0, "mimeType": "text/javascript; charset=UTF-8", "comment": ""}, "redirectURL": "", "headersSize": 885, "bodySize": 9621, "comment": ""}, "cache": {}, "timings": {"comment": "", "receive": 0, "connect": -1, "blocked": -1, "send": 0, "wait": 21, "dns": -1, "ssl": -1}, "serverIPAddress": "142.250.217.67", "comment": "", "time": 21}, {"pageref": "Carter Thomson", "startedDateTime": "2021-10-18T00:07:42.089-06:00", "request": {"method": "GET", "url": "https://www.gstatic.com/_/atari/_/js/k=atari.vw.en_US.-uc1e11mbic.O/d=0/rs=AGEqA5mq1x26X6hQffmM02K3S-EwBTeLiA/m=Y9atKf,NTMZac,sy2a,gJzDyc,sy2m,uY3Nvd,syh,syj,HYv29e", "httpVersion": "HTTP/1.1", "cookies": [], "headers": [{"name": "Host", "value": "www.gstatic.com"}, {"name": "Connection", "value": "keep-alive"}, {"name": "sec-ch-ua", "value": "\"Chromium\";v=\"94\", \"Google Chrome\";v=\"94\", \";Not A Brand\";v=\"99\""}, {"name": "sec-ch-ua-mobile", "value": "?0"}, {"name": "User-Agent", "value": "Mozilla/5.0 (Windows NT 10.0; Win64; x64) AppleWebKit/537.36 (KHTML, like Gecko) Chrome/94.0.4606.81 Safari/537.36"}, {"name": "sec-ch-ua-platform", "value": "\"Windows\""}, {"name": "Accept", "value": "*/*"}, {"name": "Sec-Fetch-Site", "value": "cross-site"}, {"name": "Sec-Fetch-Mode", "value": "no-cors"}, {"name": "Sec-Fetch-Dest", "value": "script"}, {"name": "Referer", "value": "https://www.carterthomson.com/"}, {"name": "Accept-Encoding", "value": "gzip, deflate, br"}, {"name": "Accept-Language", "value": "en-US,en;q=0.9"}], "queryString": [], "headersSize": 665, "bodySize": 0, "comment": ""}, "response": {"status": 200, "statusText": "OK", "httpVersion": "HTTP/1.1", "cookies": [], "headers": [{"name": "Accept-Ranges", "value": "bytes"}, {"name": "Vary", "value": "Accept-Encoding"}, {"name": "Content-Encoding", "value": "gzip"}, {"name": "Content-Type", "value": "text/javascript; charset=UTF-8"}, {"name": "Access-Control-Allow-Origin", "value": "*"}, {"name": "Cross-Origin-Resource-Policy", "value": "cross-origin"}, {"name": "Cross-Origin-Opener-Policy-Report-Only", "value": "same-origin; report-to=\"apps-sites\""}, {"name": "Report-To", "value": "{\"group\":\"apps-sites\",\"max_age\":2592000,\"endpoints\":[{\"url\":\"https://csp.withgoogle.com/csp/report-to/apps-sites\"}]}"}, {"name": "Content-Length", "value": "7071"}, {"name": "Date", "value": "Mon, 11 Oct 2021 14:31:09 GMT"}, {"name": "Expires", "value": "Tue, 11 Oct 2022 14:31:09 GMT"}, {"name": "Last-Modified", "value": "Tue, 05 Oct 2021 12:34:22 GMT"}, {"name": "X-Content-Type-Options", "value": "nosniff"}, {"name": "Server", "value": "sffe"}, {"name": "X-XSS-Protection", "value": "0"}, {"name": "Cache-Control", "value": "public, max-age=31536000"}, {"name": "Age", "value": "574592"}, {"name": "Alt-Svc", "value": "h3=\":443\"; ma=2592000,h3-29=\":443\"; ma=2592000,h3-T051=\":443\"; ma=2592000,h3-Q050=\":443\"; ma=2592000,h3-Q046=\":443\"; ma=2592000,h3-Q043=\":443\"; ma=2592000,quic=\":443\"; ma=2592000; v=\"46,43\""}], "content": {"size": 0, "mimeType": "text/javascript; charset=UTF-8", "comment": ""}, "redirectURL": "", "headersSize": 885, "bodySize": 7071, "comment": ""}, "cache": {}, "timings": {"comment": "", "receive": 1, "connect": -1, "blocked": -1, "send": 0, "wait": 19, "dns": -1, "ssl": -1}, "serverIPAddress": "142.250.217.67", "comment": "", "time": 21}, {"pageref": "Carter Thomson", "startedDateTime": "2021-10-18T00:07:42.093-06:00", "request": {"method": "POST", "url": "https://www.carterthomson.com/_/view/logImpressions?authuser=0", "httpVersion": "HTTP/1.1", "cookies": [], "headers": [{"name": "Host", "value": "www.carterthomson.com"}, {"name": "Connection", "value": "keep-alive"}, {"name": "Content-Length", "value": "2597"}, {"name": "sec-ch-ua", "value": "\"Chromium\";v=\"94\", \"Google Chrome\";v=\"94\", \";Not A Brand\";v=\"99\""}, {"name": "sec-ch-ua-mobile", "value": "?0"}, {"name": "User-Agent", "value": "Mozilla/5.0 (Windows NT 10.0; Win64; x64) AppleWebKit/537.36 (KHTML, like Gecko) Chrome/94.0.4606.81 Safari/537.36"}, {"name": "sec-ch-ua-platform", "value": "\"Windows\""}, {"name": "Content-Type", "value": "application/x-www-form-urlencoded;charset=UTF-8"}, {"name": "Accept", "value": "*/*"}, {"name": "Origin", "value": "https://www.carterthomson.com"}, {"name": "Sec-Fetch-Site", "value": "same-origin"}, {"name": "Sec-Fetch-Mode", "value": "cors"}, {"name": "Sec-Fetch-Dest", "value": "empty"}, {"name": "Referer", "value": "https://www.carterthomson.com/"}, {"name": "Accept-Encoding", "value": "gzip, deflate, br"}, {"name": "Accept-Language", "value": "en-US,en;q=0.9"}], "queryString": [{"name": "authuser", "value": "0"}], "headersSize": 685, "bodySize": 2597, "comment": ""}, "response": {"status": 200, "statusText": "OK", "httpVersion": "HTTP/1.1", "cookies": [], "headers": [{"name": "Content-Type", "value": "application/json; charset=utf-8"}, {"name": "Cache-Control", "value": "no-cache, no-store, max-age=0, must-revalidate"}, {"name": "Pragma", "value": "no-cache"}, {"name": "Expires", "value": "Mon, 01 Jan 1990 00:00:00 GMT"}, {"name": "Date", "value": "Mon, 18 Oct 2021 06:07:42 GMT"}, {"name": "Content-Disposition", "value": "attachment; filename=\"response.bin\"; filename*=UTF-8''response.bin"}, {"name": "X-Content-Type-Options", "value": "nosniff"}, {"name": "Cross-Origin-Opener-Policy-Report-Only", "value": "same-origin; report-to=\"AZM8irbjJqj1AV5BHD51MdaHh7lpD_Vlv2gcHw7IpJALMgk2VS4\""}, {"name": "Server", "value": "ESF"}, {"name": "X-XSS-Protection", "value": "0"}, {"name": "X-Frame-Options", "value": "SAMEORIGIN"}, {"name": "Content-Encoding", "value": "gzip"}, {"name": "Transfer-Encoding", "value": "chunked"}], "content": {"size": 0, "mimeType": "application/json; charset=utf-8", "comment": ""}, "redirectURL": "", "headersSize": 581, "bodySize": 42, "comment": ""}, "cache": {}, "timings": {"comment": "", "receive": 0, "connect": -1, "blocked": -1, "send": 0, "wait": 124, "dns": -1, "ssl": -1}, "serverIPAddress": "142.250.217.83", "comment": "", "time": 124}, {"pageref": "Carter Thomson", "startedDateTime": "2021-10-18T00:07:42.095-06:00", "request": {"method": "GET", "url": "https://fonts.gstatic.com/s/lato/v20/S6u9w4BMUTPHh7USSwiPGQ.woff2", "httpVersion": "HTTP/1.1", "cookies": [], "headers": [{"name": "Host", "value": "fonts.gstatic.com"}, {"name": "Connection", "value": "keep-alive"}, {"name": "sec-ch-ua", "value": "\"Chromium\";v=\"94\", \"Google Chrome\";v=\"94\", \";Not A Brand\";v=\"99\""}, {"name": "Origin", "value": "https://www.carterthomson.com"}, {"name": "sec-ch-ua-mobile", "value": "?0"}, {"name": "User-Agent", "value": "Mozilla/5.0 (Windows NT 10.0; Win64; x64) AppleWebKit/537.36 (KHTML, like Gecko) Chrome/94.0.4606.81 Safari/537.36"}, {"name": "sec-ch-ua-platform", "value": "\"Windows\""}, {"name": "Accept", "value": "*/*"}, {"name": "Sec-Fetch-Site", "value": "cross-site"}, {"name": "Sec-Fetch-Mode", "value": "cors"}, {"name": "Sec-Fetch-Dest", "value": "font"}, {"name": "Referer", "value": "https://fonts.googleapis.com/"}, {"name": "Accept-Encoding", "value": "gzip, deflate, br"}, {"name": "Accept-Language", "value": "en-US,en;q=0.9"}], "queryString": [], "headersSize": 599, "bodySize": 0, "comment": ""}, "response": {"status": 200, "statusText": "OK", "httpVersion": "HTTP/1.1", "cookies": [], "headers": [{"name": "Accept-Ranges", "value": "bytes"}, {"name": "Content-Type", "value": "font/woff2"}, {"name": "Access-Control-Allow-Origin", "value": "*"}, {"name": "Content-Security-Policy-Report-Only", "value": "require-trusted-types-for 'script'; report-uri https://csp.withgoogle.com/csp/apps-themes"}, {"name": "Cross-Origin-Resource-Policy", "value": "cross-origin"}, {"name": "Timing-Allow-Origin", "value": "*"}, {"name": "Content-Length", "value": "23248"}, {"name": "Date", "value": "Wed, 13 Oct 2021 23:59:30 GMT"}, {"name": "Expires", "value": "Thu, 13 Oct 2022 23:59:30 GMT"}, {"name": "Last-Modified", "value": "Tue, 10 Aug 2021 00:18:53 GMT"}, {"name": "X-Content-Type-Options", "value": "nosniff"}, {"name": "Server", "value": "sffe"}, {"name": "X-XSS-Protection", "value": "0"}, {"name": "Age", "value": "367691"}, {"name": "Cache-Control", "value": "public, max-age=31536000"}, {"name": "Alt-Svc", "value": "h3=\":443\"; ma=2592000,h3-29=\":443\"; ma=2592000,h3-T051=\":443\"; ma=2592000,h3-Q050=\":443\"; ma=2592000,h3-Q046=\":443\"; ma=2592000,h3-Q043=\":443\"; ma=2592000,quic=\":443\"; ma=2592000; v=\"46,43\""}], "content": {"size": 0, "mimeType": "font/woff2", "comment": ""}, "redirectURL": "", "headersSize": 765, "bodySize": 23248, "comment": ""}, "cache": {}, "timings": {"comment": "", "receive": 20, "connect": -1, "blocked": -1, "send": 0, "wait": 22, "dns": -1, "ssl": -1}, "serverIPAddress": "142.251.33.99", "comment": "", "time": 43}, {"pageref": "Carter Thomson", "startedDateTime": "2021-10-18T00:07:42.097-06:00", "request": {"method": "GET", "url": "https://fonts.gstatic.com/s/lato/v20/S6uyw4BMUTPHjx4wXg.woff2", "httpVersion": "HTTP/1.1", "cookies": [], "headers": [{"name": "Host", "value": "fonts.gstatic.com"}, {"name": "Connection", "value": "keep-alive"}, {"name": "sec-ch-ua", "value": "\"Chromium\";v=\"94\", \"Google Chrome\";v=\"94\", \";Not A Brand\";v=\"99\""}, {"name": "Origin", "value": "https://www.carterthomson.com"}, {"name": "sec-ch-ua-mobile", "value": "?0"}, {"name": "User-Agent", "value": "Mozilla/5.0 (Windows NT 10.0; Win64; x64) AppleWebKit/537.36 (KHTML, like Gecko) Chrome/94.0.4606.81 Safari/537.36"}, {"name": "sec-ch-ua-platform", "value": "\"Windows\""}, {"name": "Accept", "value": "*/*"}, {"name": "Sec-Fetch-Site", "value": "cross-site"}, {"name": "Sec-Fetch-Mode", "value": "cors"}, {"name": "Sec-Fetch-Dest", "value": "font"}, {"name": "Referer", "value": "https://fonts.googleapis.com/"}, {"name": "Accept-Encoding", "value": "gzip, deflate, br"}, {"name": "Accept-Language", "value": "en-US,en;q=0.9"}], "queryString": [], "headersSize": 595, "bodySize": 0, "comment": ""}, "response": {"status": 200, "statusText": "OK", "httpVersion": "HTTP/1.1", "cookies": [], "headers": [{"name": "Accept-Ranges", "value": "bytes"}, {"name": "Content-Type", "value": "font/woff2"}, {"name": "Access-Control-Allow-Origin", "value": "*"}, {"name": "Content-Security-Policy-Report-Only", "value": "require-trusted-types-for 'script'; report-uri https://csp.withgoogle.com/csp/apps-themes"}, {"name": "Cross-Origin-Resource-Policy", "value": "cross-origin"}, {"name": "Timing-Allow-Origin", "value": "*"}, {"name": "Content-Length", "value": "23484"}, {"name": "Date", "value": "Mon, 11 Oct 2021 17:04:58 GMT"}, {"name": "Expires", "value": "Tue, 11 Oct 2022 17:04:58 GMT"}, {"name": "Last-Modified", "value": "Tue, 10 Aug 2021 00:19:01 GMT"}, {"name": "X-Content-Type-Options", "value": "nosniff"}, {"name": "Server", "value": "sffe"}, {"name": "X-XSS-Protection", "value": "0"}, {"name": "Age", "value": "565363"}, {"name": "Cache-Control", "value": "public, max-age=31536000"}, {"name": "Alt-Svc", "value": "h3=\":443\"; ma=2592000,h3-29=\":443\"; ma=2592000,h3-T051=\":443\"; ma=2592000,h3-Q050=\":443\"; ma=2592000,h3-Q046=\":443\"; ma=2592000,h3-Q043=\":443\"; ma=2592000,quic=\":443\"; ma=2592000; v=\"46,43\""}], "content": {"size": 0, "mimeType": "font/woff2", "comment": ""}, "redirectURL": "", "headersSize": 765, "bodySize": 23484, "comment": ""}, "cache": {}, "timings": {"comment": "", "receive": 21, "connect": 49, "blocked": 0, "send": 0, "wait": 20, "dns": 0, "ssl": 21}, "serverIPAddress": "142.251.33.99", "comment": "", "time": 92}, {"pageref": "Carter Thomson", "startedDateTime": "2021-10-18T00:07:42.107-06:00", "request": {"method": "GET", "url": "https://www.gstatic.com/_/atari/_/js/k=atari.vw.en_US.-uc1e11mbic.O/d=0/rs=AGEqA5mq1x26X6hQffmM02K3S-EwBTeLiA/m=syr,sys,syt,syv,fuVYe,vVEdxc,syy,syx,syz,CG0Qwb", "httpVersion": "HTTP/1.1", "cookies": [], "headers": [{"name": "Host", "value": "www.gstatic.com"}, {"name": "Connection", "value": "keep-alive"}, {"name": "sec-ch-ua", "value": "\"Chromium\";v=\"94\", \"Google Chrome\";v=\"94\", \";Not A Brand\";v=\"99\""}, {"name": "sec-ch-ua-mobile", "value": "?0"}, {"name": "User-Agent", "value": "Mozilla/5.0 (Windows NT 10.0; Win64; x64) AppleWebKit/537.36 (KHTML, like Gecko) Chrome/94.0.4606.81 Safari/537.36"}, {"name": "sec-ch-ua-platform", "value": "\"Windows\""}, {"name": "Accept", "value": "*/*"}, {"name": "Sec-Fetch-Site", "value": "cross-site"}, {"name": "Sec-Fetch-Mode", "value": "no-cors"}, {"name": "Sec-Fetch-Dest", "value": "script"}, {"name": "Referer", "value": "https://www.carterthomson.com/"}, {"name": "Accept-Encoding", "value": "gzip, deflate, br"}, {"name": "Accept-Language", "value": "en-US,en;q=0.9"}], "queryString": [], "headersSize": 660, "bodySize": 0, "comment": ""}, "response": {"status": 200, "statusText": "OK", "httpVersion": "HTTP/1.1", "cookies": [], "headers": [{"name": "Accept-Ranges", "value": "bytes"}, {"name": "Vary", "value": "Accept-Encoding"}, {"name": "Content-Encoding", "value": "gzip"}, {"name": "Content-Type", "value": "text/javascript; charset=UTF-8"}, {"name": "Access-Control-Allow-Origin", "value": "*"}, {"name": "Cross-Origin-Resource-Policy", "value": "cross-origin"}, {"name": "Cross-Origin-Opener-Policy-Report-Only", "value": "same-origin; report-to=\"apps-sites\""}, {"name": "Report-To", "value": "{\"group\":\"apps-sites\",\"max_age\":2592000,\"endpoints\":[{\"url\":\"https://csp.withgoogle.com/csp/report-to/apps-sites\"}]}"}, {"name": "Content-Length", "value": "11424"}, {"name": "Date", "value": "Mon, 11 Oct 2021 14:31:10 GMT"}, {"name": "Expires", "value": "Tue, 11 Oct 2022 14:31:10 GMT"}, {"name": "Last-Modified", "value": "Tue, 05 Oct 2021 12:34:22 GMT"}, {"name": "X-Content-Type-Options", "value": "nosniff"}, {"name": "Server", "value": "sffe"}, {"name": "X-XSS-Protection", "value": "0"}, {"name": "Cache-Control", "value": "public, max-age=31536000"}, {"name": "Age", "value": "574591"}, {"name": "Alt-Svc", "value": "h3=\":443\"; ma=2592000,h3-29=\":443\"; ma=2592000,h3-T051=\":443\"; ma=2592000,h3-Q050=\":443\"; ma=2592000,h3-Q046=\":443\"; ma=2592000,h3-Q043=\":443\"; ma=2592000,quic=\":443\"; ma=2592000; v=\"46,43\""}], "content": {"size": 0, "mimeType": "text/javascript; charset=UTF-8", "comment": ""}, "redirectURL": "", "headersSize": 886, "bodySize": 11424, "comment": ""}, "cache": {}, "timings": {"comment": "", "receive": 0, "connect": -1, "blocked": -1, "send": 0, "wait": 32, "dns": -1, "ssl": -1}, "serverIPAddress": "142.250.217.67", "comment": "", "time": 33}, {"pageref": "Carter Thomson", "startedDateTime": "2021-10-18T00:07:42.607-06:00", "request": {"method": "GET", "url": "https://ssl.gstatic.com/atari/images/simple-header-blended-small.png", "httpVersion": "HTTP/1.1", "cookies": [], "headers": [{"name": "Host", "value": "ssl.gstatic.com"}, {"name": "Connection", "value": "keep-alive"}, {"name": "sec-ch-ua", "value": "\"Chromium\";v=\"94\", \"Google Chrome\";v=\"94\", \";Not A Brand\";v=\"99\""}, {"name": "sec-ch-ua-mobile", "value": "?0"}, {"name": "User-Agent", "value": "Mozilla/5.0 (Windows NT 10.0; Win64; x64) AppleWebKit/537.36 (KHTML, like Gecko) Chrome/94.0.4606.81 Safari/537.36"}, {"name": "sec-ch-ua-platform", "value": "\"Windows\""}, {"name": "Accept", "value": "image/avif,image/webp,image/apng,image/svg+xml,image/*,*/*;q=0.8"}, {"name": "Sec-Fetch-Site", "value": "cross-site"}, {"name": "Sec-Fetch-Mode", "value": "no-cors"}, {"name": "Sec-Fetch-Dest", "value": "image"}, {"name": "Referer", "value": "https://www.carterthomson.com/"}, {"name": "Accept-Encoding", "value": "gzip, deflate, br"}, {"name": "Accept-Language", "value": "en-US,en;q=0.9"}], "queryString": [], "headersSize": 629, "bodySize": 0, "comment": ""}, "response": {"status": 200, "statusText": "OK", "httpVersion": "HTTP/1.1", "cookies": [], "headers": [{"name": "Accept-Ranges", "value": "bytes"}, {"name": "Content-Type", "value": "image/png"}, {"name": "Access-Control-Allow-Origin", "value": "*"}, {"name": "Cross-Origin-Resource-Policy", "value": "cross-origin"}, {"name": "Content-Length", "value": "297036"}, {"name": "Date", "value": "Sat, 16 Oct 2021 19:59:24 GMT"}, {"name": "Expires", "value": "Sun, 16 Oct 2022 19:59:24 GMT"}, {"name": "Last-Modified", "value": "Thu, 03 Oct 2019 10:15:00 GMT"}, {"name": "X-Content-Type-Options", "value": "nosniff"}, {"name": "Server", "value": "sffe"}, {"name": "X-XSS-Protection", "value": "0"}, {"name": "Age", "value": "122898"}, {"name": "Cache-Control", "value": "public, max-age=31536000"}, {"name": "Alt-Svc", "value": "h3=\":443\"; ma=2592000,h3-29=\":443\"; ma=2592000,h3-T051=\":443\"; ma=2592000,h3-Q050=\":443\"; ma=2592000,h3-Q046=\":443\"; ma=2592000,h3-Q043=\":443\"; ma=2592000,quic=\":443\"; ma=2592000; v=\"46,43\""}], "content": {"size": 0, "mimeType": "image/png", "comment": ""}, "redirectURL": "", "headersSize": 613, "bodySize": 297036, "comment": ""}, "cache": {}, "timings": {"comment": "", "receive": 84, "connect": 639, "blocked": 0, "send": 0, "wait": 21, "dns": 0, "ssl": 618}, "serverIPAddress": "142.251.33.67", "comment": "", "time": 746}, {"pageref": "Carter Thomson", "startedDateTime": "2021-10-18T00:07:43.580-06:00", "request": {"method": "GET", "url": "https://lh4.googleusercontent.com/qJ1K1V0afgKz3Cd1Q3GJx11MkTZl8cWyPOuijo5Fx0iCpzi-_B_El-fbhHqnpNOZgtqLB9F5zjYC_ZR9UqJMcbs=w1280", "httpVersion": "HTTP/1.1", "cookies": [], "headers": [{"name": "Host", "value": "lh4.googleusercontent.com"}, {"name": "Connection", "value": "keep-alive"}, {"name": "sec-ch-ua", "value": "\"Chromium\";v=\"94\", \"Google Chrome\";v=\"94\", \";Not A Brand\";v=\"99\""}, {"name": "sec-ch-ua-mobile", "value": "?0"}, {"name": "User-Agent", "value": "Mozilla/5.0 (Windows NT 10.0; Win64; x64) AppleWebKit/537.36 (KHTML, like Gecko) Chrome/94.0.4606.81 Safari/537.36"}, {"name": "sec-ch-ua-platform", "value": "\"Windows\""}, {"name": "Accept", "value": "image/avif,image/webp,image/apng,image/svg+xml,image/*,*/*;q=0.8"}, {"name": "Sec-Fetch-Site", "value": "cross-site"}, {"name": "Sec-Fetch-Mode", "value": "no-cors"}, {"name": "Sec-Fetch-Dest", "value": "image"}, {"name": "Referer", "value": "https://www.carterthomson.com/"}, {"name": "Accept-Encoding", "value": "gzip, deflate, br"}, {"name": "Accept-Language", "value": "en-US,en;q=0.9"}], "queryString": [], "headersSize": 688, "bodySize": 0, "comment": ""}, "response": {"status": 200, "statusText": "OK", "httpVersion": "HTTP/1.1", "cookies": [], "headers": [{"name": "Access-Control-Expose-Headers", "value": "Content-Length"}, {"name": "ETag", "value": "\"v1\""}, {"name": "Expires", "value": "Tue, 19 Oct 2021 06:07:43 GMT"}, {"name": "Cache-Control", "value": "public, max-age=86400, no-transform"}, {"name": "Content-Disposition", "value": "inline;filename=\"AF1QipPzl13ZofanWbDIHVXsFWqEsJfdryV-b4BzFpPT=w3024-h4032.jpg\""}, {"name": "Content-Type", "value": "image/jpeg"}, {"name": "Vary", "value": "Origin"}, {"name": "Access-Control-Allow-Origin", "value": "*"}, {"name": "Timing-Allow-Origin", "value": "*"}, {"name": "X-Content-Type-Options", "value": "nosniff"}, {"name": "Date", "value": "Mon, 18 Oct 2021 06:07:43 GMT"}, {"name": "Server", "value": "fife"}, {"name": "Content-Length", "value": "434640"}, {"name": "X-XSS-Protection", "value": "0"}, {"name": "Alt-Svc", "value": "h3=\":443\"; ma=2592000,h3-29=\":443\"; ma=2592000,h3-T051=\":443\"; ma=2592000,h3-Q050=\":443\"; ma=2592000,h3-Q046=\":443\"; ma=2592000,h3-Q043=\":443\"; ma=2592000,quic=\":443\"; ma=2592000; v=\"46,43\""}], "content": {"size": 0, "mimeType": "image/jpeg", "comment": ""}, "redirectURL": "", "headersSize": 698, "bodySize": 434640, "comment": ""}, "cache": {}, "timings": {"comment": "", "receive": 110, "connect": 1615, "blocked": 0, "send": 0, "wait": 144, "dns": 8, "ssl": 1592}, "serverIPAddress": "142.250.217.65", "comment": "", "time": 1878}, {"pageref": "Carter Thomson", "startedDateTime": "2021-10-18T00:07:43.840-06:00", "request": {"method": "GET", "url": "https://ssl.gstatic.com/atari/images/public/favicon.ico", "httpVersion": "HTTP/1.1", "cookies": [], "headers": [{"name": "Host", "value": "ssl.gstatic.com"}, {"name": "Connection", "value": "keep-alive"}, {"name": "sec-ch-ua", "value": "\"Chromium\";v=\"94\", \"Google Chrome\";v=\"94\", \";Not A Brand\";v=\"99\""}, {"name": "sec-ch-ua-mobile", "value": "?0"}, {"name": "User-Agent", "value": "Mozilla/5.0 (Windows NT 10.0; Win64; x64) AppleWebKit/537.36 (KHTML, like Gecko) Chrome/94.0.4606.81 Safari/537.36"}, {"name": "sec-ch-ua-platform", "value": "\"Windows\""}, {"name": "Accept", "value": "image/avif,image/webp,image/apng,image/svg+xml,image/*,*/*;q=0.8"}, {"name": "Sec-Fetch-Site", "value": "cross-site"}, {"name": "Sec-Fetch-Mode", "value": "no-cors"}, {"name": "Sec-Fetch-Dest", "value": "image"}, {"name": "Referer", "value": "https://www.carterthomson.com/"}, {"name": "Accept-Encoding", "value": "gzip, deflate, br"}, {"name": "Accept-Language", "value": "en-US,en;q=0.9"}], "queryString": [], "headersSize": 616, "bodySize": 0, "comment": ""}, "response": {"status": 0, "statusText": "", "httpVersion": "unknown", "cookies": [], "headers": [], "content": {"size": 0, "mimeType": "", "comment": ""}, "redirectURL": "", "headersSize": -1, "bodySize": -1, "comment": "", "_error": "No response received"}, "cache": {}, "timings": {"comment": "", "receive": 0, "connect": -1, "blocked": -1, "send": 0, "wait": 0, "dns": -1, "ssl": -1}, "serverIPAddress": "142.251.33.67", "comment": "", "time": 0}], "comment": ""}}